Classfile /home/omkar/personal/tokyo_escape/escapeAnalysis/benchmark_dump/avrora_in/org/dacapo/harness/Benchmark.class
  Last modified 11-Sept-2023; size 15188 bytes
  SHA-256 checksum 984bd4097e73f817b052b827ebb1a72aba7c9d58ff9f1e2d3d36f3e601bbd212
  Compiled from "Benchmark.java"
public abstract class org.dacapo.harness.Benchmark
  minor version: 0
  major version: 52
  flags: (0x0421) ACC_PUBLIC, ACC_SUPER, ACC_ABSTRACT
  this_class: #72                         // org/dacapo/harness/Benchmark
  super_class: #212                       // java/lang/Object
  interfaces: 0, fields: 22, methods: 37, attributes: 1
Constant pool:
    #1 = Fieldref           #72.#382      // org/dacapo/harness/Benchmark.iteration:I
    #2 = Methodref          #72.#383      // org/dacapo/harness/Benchmark.prepare:(Ljava/lang/String;)V
    #3 = Fieldref           #72.#384      // org/dacapo/harness/Benchmark.savedOut:Ljava/io/PrintStream;
    #4 = Methodref          #385.#386     // java/lang/System.setOut:(Ljava/io/PrintStream;)V
    #5 = Fieldref           #72.#387      // org/dacapo/harness/Benchmark.savedErr:Ljava/io/PrintStream;
    #6 = Methodref          #385.#388     // java/lang/System.setErr:(Ljava/io/PrintStream;)V
    #7 = Methodref          #72.#389      // org/dacapo/harness/Benchmark.preIteration:(Ljava/lang/String;)V
    #8 = Fieldref           #72.#390      // org/dacapo/harness/Benchmark.preIterationGC:Z
    #9 = Methodref          #385.#391     // java/lang/System.gc:()V
   #10 = Fieldref           #72.#392      // org/dacapo/harness/Benchmark.config:Lorg/dacapo/parser/Config;
   #11 = Fieldref           #393.#394     // org/dacapo/parser/Config.name:Ljava/lang/String;
   #12 = Methodref          #395.#396     // org/dacapo/harness/Callback.start:(Ljava/lang/String;)V
   #13 = Methodref          #385.#397     // java/lang/System.currentTimeMillis:()J
   #14 = Methodref          #72.#398      // org/dacapo/harness/Benchmark.startIteration:()V
   #15 = Methodref          #72.#399      // org/dacapo/harness/Benchmark.iterate:(Ljava/lang/String;)V
   #16 = Methodref          #72.#400      // org/dacapo/harness/Benchmark.stopIteration:()V
   #17 = Methodref          #395.#401     // org/dacapo/harness/Callback.stop:(J)V
   #18 = Methodref          #72.#402      // org/dacapo/harness/Benchmark.validate:(Ljava/lang/String;)Z
   #19 = Methodref          #395.#403     // org/dacapo/harness/Callback.complete:(Ljava/lang/String;Z)V
   #20 = Methodref          #72.#404      // org/dacapo/harness/Benchmark.postIteration:(Ljava/lang/String;)V
   #21 = Methodref          #72.#405      // org/dacapo/harness/Benchmark."<init>":(Lorg/dacapo/parser/Config;Ljava/io/File;Z)V
   #22 = Methodref          #212.#406     // java/lang/Object."<init>":()V
   #23 = Fieldref           #72.#407      // org/dacapo/harness/Benchmark.silent:Z
   #24 = Fieldref           #72.#408      // org/dacapo/harness/Benchmark.scratch:Ljava/io/File;
   #25 = Methodref          #72.#409      // org/dacapo/harness/Benchmark.initialize:()V
   #26 = Methodref          #385.#410     // java/lang/System.getProperties:()Ljava/util/Properties;
   #27 = Fieldref           #72.#411      // org/dacapo/harness/Benchmark.savedSystemProperties:Ljava/util/Properties;
   #28 = String             #412          // java.util.logging.config.file
   #29 = Class              #413          // java/lang/StringBuilder
   #30 = Methodref          #29.#406      // java/lang/StringBuilder."<init>":()V
   #31 = Methodref          #29.#414      // java/lang/StringBuilder.append:(Ljava/lang/String;)Ljava/lang/StringBuilder;
   #32 = String             #415          // .log
   #33 = Methodref          #29.#416      // java/lang/StringBuilder.toString:()Ljava/lang/String;
   #34 = Methodref          #72.#417      // org/dacapo/harness/Benchmark.fileInScratch:(Ljava/lang/String;)Ljava/lang/String;
   #35 = Methodref          #385.#418     // java/lang/System.setProperty:(Ljava/lang/String;Ljava/lang/String;)Ljava/lang/String;
   #36 = Fieldref           #385.#419     // java/lang/System.out:Ljava/io/PrintStream;
   #37 = Fieldref           #72.#420      // org/dacapo/harness/Benchmark.out:Lorg/dacapo/harness/TeePrintStream;
   #38 = Class              #421          // org/dacapo/harness/TeePrintStream
   #39 = Class              #422          // java/io/File
   #40 = String             #423          // stdout.log
   #41 = Methodref          #39.#424      // java/io/File."<init>":(Ljava/io/File;Ljava/lang/String;)V
   #42 = Methodref          #38.#425      // org/dacapo/harness/TeePrintStream."<init>":(Ljava/io/OutputStream;Ljava/io/File;)V
   #43 = Methodref          #38.#426      // org/dacapo/harness/TeePrintStream.enableOutput:(Z)V
   #44 = Fieldref           #385.#427     // java/lang/System.err:Ljava/io/PrintStream;
   #45 = Fieldref           #72.#428      // org/dacapo/harness/Benchmark.err:Lorg/dacapo/harness/TeePrintStream;
   #46 = String             #429          // stderr.log
   #47 = Methodref          #72.#430      // org/dacapo/harness/Benchmark.prepareJars:()V
   #48 = Methodref          #431.#432     // org/dacapo/harness/DacapoClassLoader.create:(Lorg/dacapo/parser/Config;Ljava/io/File;)Lorg/dacapo/harness/DacapoClassLoader;
   #49 = Fieldref           #72.#433      // org/dacapo/harness/Benchmark.loader:Ljava/lang/ClassLoader;
   #50 = Methodref          #72.#434      // org/dacapo/harness/Benchmark.prepare:()V
   #51 = Methodref          #29.#435      // java/lang/StringBuilder.append:(Ljava/lang/Object;)Ljava/lang/StringBuilder;
   #52 = String             #436          // /jar
   #53 = Methodref          #39.#437      // java/io/File."<init>":(Ljava/lang/String;)V
   #54 = Methodref          #39.#438      // java/io/File.exists:()Z
   #55 = Methodref          #39.#439      // java/io/File.mkdir:()Z
   #56 = Fieldref           #393.#440     // org/dacapo/parser/Config.jars:[Ljava/lang/String;
   #57 = String             #441          // jar/
   #58 = Methodref          #72.#442      // org/dacapo/harness/Benchmark.extractFileResource:(Ljava/lang/String;Ljava/io/File;)V
   #59 = String             #443          // dat/
   #60 = String             #444          // .zip
   #61 = Methodref          #72.#445      // org/dacapo/harness/Benchmark.unpackZipFileResource:(Ljava/lang/String;Ljava/io/File;)V
   #62 = Fieldref           #72.#446      // org/dacapo/harness/Benchmark.verbose:Z
   #63 = Methodref          #393.#447     // org/dacapo/parser/Config.preprocessArgs:(Ljava/lang/String;Ljava/io/File;)[Ljava/lang/String;
   #64 = String             #448          // Benchmark parameters:
   #65 = Methodref          #449.#450     // java/io/PrintStream.print:(Ljava/lang/String;)V
   #66 = String             #451          //
   #67 = Methodref          #449.#452     // java/io/PrintStream.println:()V
   #68 = Fieldref           #72.#453      // org/dacapo/harness/Benchmark.preserve:Z
   #69 = Methodref          #72.#454      // org/dacapo/harness/Benchmark.postIterationCleanup:(Ljava/lang/String;)V
   #70 = String             #455          // startIteration()
   #71 = Methodref          #449.#456     // java/io/PrintStream.println:(Ljava/lang/String;)V
   #72 = Class              #457          // org/dacapo/harness/Benchmark
   #73 = String             #458          // dacapo.timeout.dialation
   #74 = Fieldref           #72.#459      // org/dacapo/harness/Benchmark.timeoutDialation:Ljava/lang/String;
   #75 = Methodref          #76.#460      // java/util/Properties.clone:()Ljava/lang/Object;
   #76 = Class              #461          // java/util/Properties
   #77 = Methodref          #72.#462      // org/dacapo/harness/Benchmark.augmentSystemProperties:(Ljava/util/Properties;)V
   #78 = Methodref          #385.#463     // java/lang/System.setProperties:(Ljava/util/Properties;)V
   #79 = Fieldref           #72.#464      // org/dacapo/harness/Benchmark.validateOutput:Z
   #80 = Methodref          #38.#465      // org/dacapo/harness/TeePrintStream.version:()V
   #81 = Methodref          #38.#466      // org/dacapo/harness/TeePrintStream.openLog:()V
   #82 = Methodref          #72.#467      // org/dacapo/harness/Benchmark.useBenchmarkClassLoader:()V
   #83 = Methodref          #72.#468      // org/dacapo/harness/Benchmark.revertClassLoader:()V
   #84 = Methodref          #38.#469      // org/dacapo/harness/TeePrintStream.closeLog:()V
   #85 = String             #470          // stopIteration()
   #86 = Methodref          #471.#472     // java/lang/Thread.currentThread:()Ljava/lang/Thread;
   #87 = Methodref          #471.#473     // java/lang/Thread.getContextClassLoader:()Ljava/lang/ClassLoader;
   #88 = Fieldref           #72.#474      // org/dacapo/harness/Benchmark.savedClassLoader:Ljava/lang/ClassLoader;
   #89 = Methodref          #471.#475     // java/lang/Thread.setContextClassLoader:(Ljava/lang/ClassLoader;)V
   #90 = String             #476          // validate(
   #91 = Fieldref           #72.#477      // org/dacapo/harness/Benchmark.validate:Z
   #92 = Methodref          #29.#478      // java/lang/StringBuilder.append:(Z)Ljava/lang/StringBuilder;
   #93 = String             #479          // )
   #94 = Fieldref           #72.#480      // org/dacapo/harness/Benchmark.validationReport:Z
   #95 = Fieldref           #72.#481      // org/dacapo/harness/Benchmark.valRepFile:Ljava/io/PrintWriter;
   #96 = String             #482          // Validating
   #97 = Methodref          #204.#456     // java/io/PrintWriter.println:(Ljava/lang/String;)V
   #98 = Methodref          #393.#483     // org/dacapo/parser/Config.getOutputs:(Ljava/lang/String;)Ljava/util/Set;
   #99 = InterfaceMethodref #484.#485     // java/util/Set.iterator:()Ljava/util/Iterator;
  #100 = InterfaceMethodref #486.#487     // java/util/Iterator.hasNext:()Z
  #101 = InterfaceMethodref #486.#488     // java/util/Iterator.next:()Ljava/lang/Object;
  #102 = Class              #489          // java/lang/String
  #103 = Methodref          #393.#490     // org/dacapo/parser/Config.hasDigest:(Ljava/lang/String;Ljava/lang/String;)Z
  #104 = Methodref          #393.#491     // org/dacapo/parser/Config.getDigest:(Ljava/lang/String;Ljava/lang/String;)Ljava/lang/String;
  #105 = Methodref          #393.#492     // org/dacapo/parser/Config.isTextFile:(Ljava/lang/String;Ljava/lang/String;)Z
  #106 = Methodref          #393.#493     // org/dacapo/parser/Config.filterScratch:(Ljava/lang/String;Ljava/lang/String;)Z
  #107 = Methodref          #494.#495     // org/dacapo/harness/FileDigest.get:(Ljava/lang/String;ZZLjava/io/File;)[B
  #108 = Methodref          #496.#497     // org/dacapo/harness/Digest.toString:([B)Ljava/lang/String;
  #109 = Class              #498          // java/io/FileNotFoundException
  #110 = String             #499          // <File not found>
  #111 = Class              #500          // java/io/IOException
  #112 = String             #501          // <IO exception>
  #113 = Methodref          #111.#502     // java/io/IOException.printStackTrace:()V
  #114 = String             #503          //   \"
  #115 = String             #504          // \" digest 0x
  #116 = String             #505          // ,
  #117 = String             #506          // $stdout
  #118 = Methodref          #102.#507     // java/lang/String.equals:(Ljava/lang/Object;)Z
  #119 = String             #508          // $stderr
  #120 = String             #509          // Digest validation failed for
  #121 = String             #510          // , expecting 0x
  #122 = String             #511          //  found 0x
  #123 = String             #512          // Digest validation succeeded for
  #124 = Methodref          #393.#513     // org/dacapo/parser/Config.hasLines:(Ljava/lang/String;Ljava/lang/String;)Z
  #125 = Methodref          #393.#514     // org/dacapo/parser/Config.getLines:(Ljava/lang/String;Ljava/lang/String;)I
  #126 = Methodref          #72.#515      // org/dacapo/harness/Benchmark.lineCount:(Ljava/io/File;)I
  #127 = String             #516          // File not found,
  #128 = String             #517          // \" lines
  #129 = Methodref          #29.#518      // java/lang/StringBuilder.append:(I)Ljava/lang/StringBuilder;
  #130 = String             #519          // Line count validation failed for
  #131 = String             #520          // , expecting
  #132 = String             #521          //  found
  #133 = String             #522          // Line count validation succeeded for
  #134 = Methodref          #393.#523     // org/dacapo/parser/Config.hasBytes:(Ljava/lang/String;Ljava/lang/String;)Z
  #135 = Methodref          #393.#524     // org/dacapo/parser/Config.getBytes:(Ljava/lang/String;Ljava/lang/String;)J
  #136 = Methodref          #72.#525      // org/dacapo/harness/Benchmark.byteCount:(Ljava/io/File;)J
  #137 = Long               -1l
  #139 = String             #526          // \" bytes
  #140 = Methodref          #29.#527      // java/lang/StringBuilder.append:(J)Ljava/lang/StringBuilder;
  #141 = String             #528          // Byte count validation failed for
  #142 = String             #529          // Byte count validation succeeded for
  #143 = Methodref          #393.#530     // org/dacapo/parser/Config.checkExists:(Ljava/lang/String;Ljava/lang/String;)Z
  #144 = String             #531          // Expected file
  #145 = String             #532          //  does not exist
  #146 = String             #533          // Existence validation succeeded for
  #147 = Methodref          #204.#534     // java/io/PrintWriter.flush:()V
  #148 = Methodref          #393.#535     // org/dacapo/parser/Config.isKept:(Ljava/lang/String;Ljava/lang/String;)Z
  #149 = Methodref          #72.#536      // org/dacapo/harness/Benchmark.deleteFile:(Ljava/io/File;)V
  #150 = Methodref          #72.#537      // org/dacapo/harness/Benchmark.deleteTree:(Ljava/io/File;)V
  #151 = Methodref          #538.#539     // java/lang/Class.getClassLoader:()Ljava/lang/ClassLoader;
  #152 = Methodref          #540.#541     // java/lang/ClassLoader.getResource:(Ljava/lang/String;)Ljava/net/URL;
  #153 = String             #542          // Util.getURL: returns
  #154 = Methodref          #39.#543      // java/io/File.getPath:()Ljava/lang/String;
  #155 = Methodref          #72.#544      // org/dacapo/harness/Benchmark.getURL:(Ljava/lang/String;)Ljava/net/URL;
  #156 = Class              #545          // org/dacapo/harness/DacapoException
  #157 = String             #546          // No such zip file: \"
  #158 = String             #547          // \"
  #159 = Methodref          #156.#437     // org/dacapo/harness/DacapoException."<init>":(Ljava/lang/String;)V
  #160 = Class              #548          // java/io/BufferedInputStream
  #161 = Methodref          #549.#550     // java/net/URL.openStream:()Ljava/io/InputStream;
  #162 = Methodref          #160.#551     // java/io/BufferedInputStream."<init>":(Ljava/io/InputStream;)V
  #163 = Methodref          #72.#552      // org/dacapo/harness/Benchmark.unpackZipStream:(Ljava/io/BufferedInputStream;Ljava/io/File;)V
  #164 = String             #553          // Extracting file
  #165 = String             #554          //  into
  #166 = Methodref          #39.#555      // java/io/File.getCanonicalPath:()Ljava/lang/String;
  #167 = String             #556          // No such file: \"
  #168 = Methodref          #72.#557      // org/dacapo/harness/Benchmark.fileFromInputStream:(Ljava/io/InputStream;Ljava/io/File;)V
  #169 = Class              #558          // java/util/zip/ZipInputStream
  #170 = Methodref          #169.#551     // java/util/zip/ZipInputStream."<init>":(Ljava/io/InputStream;)V
  #171 = Methodref          #169.#559     // java/util/zip/ZipInputStream.getNextEntry:()Ljava/util/zip/ZipEntry;
  #172 = String             #560          // Unpacking
  #173 = Methodref          #561.#562     // java/util/zip/ZipEntry.getName:()Ljava/lang/String;
  #174 = Methodref          #561.#563     // java/util/zip/ZipEntry.isDirectory:()Z
  #175 = Methodref          #169.#564     // java/util/zip/ZipInputStream.close:()V
  #176 = Class              #565          // java/io/FileOutputStream
  #177 = Methodref          #176.#566     // java/io/FileOutputStream."<init>":(Ljava/io/File;)V
  #178 = Class              #567          // java/io/BufferedOutputStream
  #179 = Methodref          #178.#568     // java/io/BufferedOutputStream."<init>":(Ljava/io/OutputStream;I)V
  #180 = Methodref          #569.#570     // java/io/InputStream.read:([BII)I
  #181 = Methodref          #178.#571     // java/io/BufferedOutputStream.write:([BII)V
  #182 = Methodref          #178.#534     // java/io/BufferedOutputStream.flush:()V
  #183 = Methodref          #178.#564     // java/io/BufferedOutputStream.close:()V
  #184 = String             #572          // Deleting
  #185 = Methodref          #39.#562      // java/io/File.getName:()Ljava/lang/String;
  #186 = Methodref          #39.#563      // java/io/File.isDirectory:()Z
  #187 = Methodref          #39.#573      // java/io/File.delete:()Z
  #188 = Methodref          #39.#574      // java/io/File.listFiles:()[Ljava/io/File;
  #189 = Class              #575          // java/io/BufferedReader
  #190 = Class              #576          // java/io/FileReader
  #191 = Methodref          #190.#566     // java/io/FileReader."<init>":(Ljava/io/File;)V
  #192 = Methodref          #189.#577     // java/io/BufferedReader."<init>":(Ljava/io/Reader;)V
  #193 = Methodref          #189.#578     // java/io/BufferedReader.readLine:()Ljava/lang/String;
  #194 = Methodref          #189.#564     // java/io/BufferedReader.close:()V
  #195 = Methodref          #39.#579      // java/io/File.length:()J
  #196 = Methodref          #580.#581     // org/dacapo/harness/CommandLineArgs.getSilent:()Z
  #197 = Methodref          #580.#582     // org/dacapo/harness/CommandLineArgs.getPreserve:()Z
  #198 = Methodref          #580.#583     // org/dacapo/harness/CommandLineArgs.getValidate:()Z
  #199 = Methodref          #580.#584     // org/dacapo/harness/CommandLineArgs.getValidateOutput:()Z
  #200 = Methodref          #580.#585     // org/dacapo/harness/CommandLineArgs.getPreIterationGC:()Z
  #201 = Methodref          #580.#586     // org/dacapo/harness/CommandLineArgs.getTimeoutDialation:()Ljava/lang/String;
  #202 = Methodref          #580.#587     // org/dacapo/harness/CommandLineArgs.getValidationReport:()Ljava/lang/String;
  #203 = Methodref          #72.#588      // org/dacapo/harness/Benchmark.enableValidationReport:(Ljava/lang/String;)V
  #204 = Class              #589          // java/io/PrintWriter
  #205 = Class              #590          // java/io/BufferedWriter
  #206 = Class              #591          // java/io/FileWriter
  #207 = Methodref          #206.#592     // java/io/FileWriter."<init>":(Ljava/lang/String;Z)V
  #208 = Methodref          #205.#593     // java/io/BufferedWriter."<init>":(Ljava/io/Writer;)V
  #209 = Methodref          #204.#593     // java/io/PrintWriter."<init>":(Ljava/io/Writer;)V
  #210 = Methodref          #385.#594     // java/lang/System.exit:(I)V
  #211 = String             #595          // 1
  #212 = Class              #596          // java/lang/Object
  #213 = Utf8               BUFFER_SIZE
  #214 = Utf8               I
  #215 = Utf8               ConstantValue
  #216 = Integer            2048
  #217 = Utf8               TIMEOUT_DIALATION_PROPERTY
  #218 = Utf8               Ljava/lang/String;
  #219 = Utf8               verbose
  #220 = Utf8               Z
  #221 = Utf8               silent
  #222 = Utf8               validateOutput
  #223 = Utf8               preIterationGC
  #224 = Utf8               validate
  #225 = Utf8               preserve
  #226 = Utf8               valRepFile
  #227 = Utf8               Ljava/io/PrintWriter;
  #228 = Utf8               validationReport
  #229 = Utf8               timeoutDialation
  #230 = Utf8               savedOut
  #231 = Utf8               Ljava/io/PrintStream;
  #232 = Utf8               savedErr
  #233 = Utf8               scratch
  #234 = Utf8               Ljava/io/File;
  #235 = Utf8               config
  #236 = Utf8               Lorg/dacapo/parser/Config;
  #237 = Utf8               loader
  #238 = Utf8               Ljava/lang/ClassLoader;
  #239 = Utf8               savedClassLoader
  #240 = Utf8               savedSystemProperties
  #241 = Utf8               Ljava/util/Properties;
  #242 = Utf8               err
  #243 = Utf8               Lorg/dacapo/harness/TeePrintStream;
  #244 = Utf8               out
  #245 = Utf8               iteration
  #246 = Utf8               method
  #247 = Utf8               Ljava/lang/reflect/Method;
  #248 = Utf8               run
  #249 = Utf8               (Lorg/dacapo/harness/Callback;Ljava/lang/String;)Z
  #250 = Utf8               Code
  #251 = Utf8               LineNumberTable
  #252 = Utf8               LocalVariableTable
  #253 = Utf8               this
  #254 = Utf8               Lorg/dacapo/harness/Benchmark;
  #255 = Utf8               callback
  #256 = Utf8               Lorg/dacapo/harness/Callback;
  #257 = Utf8               size
  #258 = Utf8               start
  #259 = Utf8               J
  #260 = Utf8               duration
  #261 = Utf8               valid
  #262 = Utf8               StackMapTable
  #263 = Class              #457          // org/dacapo/harness/Benchmark
  #264 = Class              #597          // org/dacapo/harness/Callback
  #265 = Class              #489          // java/lang/String
  #266 = Class              #598          // java/lang/Throwable
  #267 = Utf8               Exceptions
  #268 = Class              #599          // java/lang/Exception
  #269 = Utf8               <init>
  #270 = Utf8               (Lorg/dacapo/parser/Config;Ljava/io/File;)V
  #271 = Utf8               (Lorg/dacapo/parser/Config;Ljava/io/File;Z)V
  #272 = Utf8               initialize
  #273 = Utf8               ()V
  #274 = Class              #596          // java/lang/Object
  #275 = Class              #421          // org/dacapo/harness/TeePrintStream
  #276 = Utf8               prepareJars
  #277 = Utf8               i
  #278 = Utf8               file
  #279 = Class              #422          // java/io/File
  #280 = Utf8               prepare
  #281 = Utf8               (Ljava/lang/String;)V
  #282 = Utf8               preIteration
  #283 = Utf8               args
  #284 = Utf8               [Ljava/lang/String;
  #285 = Class              #284          // "[Ljava/lang/String;"
  #286 = Utf8               startIteration
  #287 = Utf8               augmentedSystemProperties
  #288 = Class              #461          // java/util/Properties
  #289 = Utf8               augmentSystemProperties
  #290 = Utf8               (Ljava/util/Properties;)V
  #291 = Utf8               systemProperties
  #292 = Utf8               iterate
  #293 = Utf8               stopIteration
  #294 = Utf8               useBenchmarkClassLoader
  #295 = Utf8               revertClassLoader
  #296 = Utf8               (Ljava/lang/String;)Z
  #297 = Utf8               digest
  #298 = Utf8               e
  #299 = Utf8               Ljava/io/FileNotFoundException;
  #300 = Utf8               Ljava/io/IOException;
  #301 = Utf8               refDigest
  #302 = Utf8               lines
  #303 = Utf8               refLines
  #304 = Utf8               bytes
  #305 = Utf8               refBytes
  #306 = Class              #600          // java/util/Iterator
  #307 = Class              #498          // java/io/FileNotFoundException
  #308 = Class              #500          // java/io/IOException
  #309 = Utf8               postIteration
  #310 = Utf8               postIterationCleanup
  #311 = Utf8               cleanup
  #312 = Utf8               getURL
  #313 = Utf8               (Ljava/lang/String;)Ljava/net/URL;
  #314 = Utf8               fn
  #315 = Utf8               cl
  #316 = Utf8               resource
  #317 = Utf8               Ljava/net/URL;
  #318 = Class              #601          // java/lang/ClassLoader
  #319 = Class              #602          // java/net/URL
  #320 = Utf8               fileInScratch
  #321 = Utf8               (Ljava/lang/String;)Ljava/lang/String;
  #322 = Utf8               name
  #323 = Utf8               unpackZipFileResource
  #324 = Utf8               (Ljava/lang/String;Ljava/io/File;)V
  #325 = Utf8               destination
  #326 = Utf8               inputStream
  #327 = Utf8               Ljava/io/BufferedInputStream;
  #328 = Utf8               extractFileResource
  #329 = Utf8               unpackZipStream
  #330 = Utf8               (Ljava/io/BufferedInputStream;Ljava/io/File;)V
  #331 = Utf8               input
  #332 = Utf8               Ljava/util/zip/ZipInputStream;
  #333 = Utf8               entry
  #334 = Utf8               Ljava/util/zip/ZipEntry;
  #335 = Class              #558          // java/util/zip/ZipInputStream
  #336 = Class              #603          // java/util/zip/ZipEntry
  #337 = Utf8               fileFromInputStream
  #338 = Utf8               (Ljava/io/InputStream;Ljava/io/File;)V
  #339 = Utf8               Ljava/io/InputStream;
  #340 = Utf8               fos
  #341 = Utf8               Ljava/io/FileOutputStream;
  #342 = Utf8               dest
  #343 = Utf8               Ljava/io/BufferedOutputStream;
  #344 = Utf8               count
  #345 = Utf8               data
  #346 = Utf8               [B
  #347 = Class              #604          // java/io/InputStream
  #348 = Class              #565          // java/io/FileOutputStream
  #349 = Class              #567          // java/io/BufferedOutputStream
  #350 = Class              #346          // "[B"
  #351 = Utf8               deleteTree
  #352 = Utf8               (Ljava/io/File;)V
  #353 = Utf8               files
  #354 = Utf8               [Ljava/io/File;
  #355 = Utf8               tree
  #356 = Class              #354          // "[Ljava/io/File;"
  #357 = Utf8               deleteFile
  #358 = Utf8               lineCount
  #359 = Utf8               (Ljava/io/File;)I
  #360 = Utf8               in
  #361 = Utf8               Ljava/io/BufferedReader;
  #362 = Class              #575          // java/io/BufferedReader
  #363 = Utf8               byteCount
  #364 = Utf8               (Ljava/io/File;)J
  #365 = Utf8               setCommandLineOptions
  #366 = Utf8               (Lorg/dacapo/harness/CommandLineArgs;)V
  #367 = Utf8               line
  #368 = Utf8               Lorg/dacapo/harness/CommandLineArgs;
  #369 = Utf8               enableValidationReport
  #370 = Utf8               filename
  #371 = Utf8               getVerbose
  #372 = Utf8               ()Z
  #373 = Utf8               getValidateOutput
  #374 = Utf8               getValidate
  #375 = Utf8               getPreserve
  #376 = Utf8               getIteration
  #377 = Utf8               ()I
  #378 = Utf8               getSilent
  #379 = Utf8               <clinit>
  #380 = Utf8               SourceFile
  #381 = Utf8               Benchmark.java
  #382 = NameAndType        #245:#214     // iteration:I
  #383 = NameAndType        #280:#281     // prepare:(Ljava/lang/String;)V
  #384 = NameAndType        #230:#231     // savedOut:Ljava/io/PrintStream;
  #385 = Class              #605          // java/lang/System
  #386 = NameAndType        #606:#607     // setOut:(Ljava/io/PrintStream;)V
  #387 = NameAndType        #232:#231     // savedErr:Ljava/io/PrintStream;
  #388 = NameAndType        #608:#607     // setErr:(Ljava/io/PrintStream;)V
  #389 = NameAndType        #282:#281     // preIteration:(Ljava/lang/String;)V
  #390 = NameAndType        #223:#220     // preIterationGC:Z
  #391 = NameAndType        #609:#273     // gc:()V
  #392 = NameAndType        #235:#236     // config:Lorg/dacapo/parser/Config;
  #393 = Class              #610          // org/dacapo/parser/Config
  #394 = NameAndType        #322:#218     // name:Ljava/lang/String;
  #395 = Class              #597          // org/dacapo/harness/Callback
  #396 = NameAndType        #258:#281     // start:(Ljava/lang/String;)V
  #397 = NameAndType        #611:#612     // currentTimeMillis:()J
  #398 = NameAndType        #286:#273     // startIteration:()V
  #399 = NameAndType        #292:#281     // iterate:(Ljava/lang/String;)V
  #400 = NameAndType        #293:#273     // stopIteration:()V
  #401 = NameAndType        #613:#614     // stop:(J)V
  #402 = NameAndType        #224:#296     // validate:(Ljava/lang/String;)Z
  #403 = NameAndType        #615:#616     // complete:(Ljava/lang/String;Z)V
  #404 = NameAndType        #309:#281     // postIteration:(Ljava/lang/String;)V
  #405 = NameAndType        #269:#271     // "<init>":(Lorg/dacapo/parser/Config;Ljava/io/File;Z)V
  #406 = NameAndType        #269:#273     // "<init>":()V
  #407 = NameAndType        #221:#220     // silent:Z
  #408 = NameAndType        #233:#234     // scratch:Ljava/io/File;
  #409 = NameAndType        #272:#273     // initialize:()V
  #410 = NameAndType        #617:#618     // getProperties:()Ljava/util/Properties;
  #411 = NameAndType        #240:#241     // savedSystemProperties:Ljava/util/Properties;
  #412 = Utf8               java.util.logging.config.file
  #413 = Utf8               java/lang/StringBuilder
  #414 = NameAndType        #619:#620     // append:(Ljava/lang/String;)Ljava/lang/StringBuilder;
  #415 = Utf8               .log
  #416 = NameAndType        #621:#622     // toString:()Ljava/lang/String;
  #417 = NameAndType        #320:#321     // fileInScratch:(Ljava/lang/String;)Ljava/lang/String;
  #418 = NameAndType        #623:#624     // setProperty:(Ljava/lang/String;Ljava/lang/String;)Ljava/lang/String;
  #419 = NameAndType        #244:#231     // out:Ljava/io/PrintStream;
  #420 = NameAndType        #244:#243     // out:Lorg/dacapo/harness/TeePrintStream;
  #421 = Utf8               org/dacapo/harness/TeePrintStream
  #422 = Utf8               java/io/File
  #423 = Utf8               stdout.log
  #424 = NameAndType        #269:#625     // "<init>":(Ljava/io/File;Ljava/lang/String;)V
  #425 = NameAndType        #269:#626     // "<init>":(Ljava/io/OutputStream;Ljava/io/File;)V
  #426 = NameAndType        #627:#628     // enableOutput:(Z)V
  #427 = NameAndType        #242:#231     // err:Ljava/io/PrintStream;
  #428 = NameAndType        #242:#243     // err:Lorg/dacapo/harness/TeePrintStream;
  #429 = Utf8               stderr.log
  #430 = NameAndType        #276:#273     // prepareJars:()V
  #431 = Class              #629          // org/dacapo/harness/DacapoClassLoader
  #432 = NameAndType        #630:#631     // create:(Lorg/dacapo/parser/Config;Ljava/io/File;)Lorg/dacapo/harness/DacapoClassLoader;
  #433 = NameAndType        #237:#238     // loader:Ljava/lang/ClassLoader;
  #434 = NameAndType        #280:#273     // prepare:()V
  #435 = NameAndType        #619:#632     // append:(Ljava/lang/Object;)Ljava/lang/StringBuilder;
  #436 = Utf8               /jar
  #437 = NameAndType        #269:#281     // "<init>":(Ljava/lang/String;)V
  #438 = NameAndType        #633:#372     // exists:()Z
  #439 = NameAndType        #634:#372     // mkdir:()Z
  #440 = NameAndType        #635:#284     // jars:[Ljava/lang/String;
  #441 = Utf8               jar/
  #442 = NameAndType        #328:#324     // extractFileResource:(Ljava/lang/String;Ljava/io/File;)V
  #443 = Utf8               dat/
  #444 = Utf8               .zip
  #445 = NameAndType        #323:#324     // unpackZipFileResource:(Ljava/lang/String;Ljava/io/File;)V
  #446 = NameAndType        #219:#220     // verbose:Z
  #447 = NameAndType        #636:#637     // preprocessArgs:(Ljava/lang/String;Ljava/io/File;)[Ljava/lang/String;
  #448 = Utf8               Benchmark parameters:
  #449 = Class              #638          // java/io/PrintStream
  #450 = NameAndType        #639:#281     // print:(Ljava/lang/String;)V
  #451 = Utf8
  #452 = NameAndType        #640:#273     // println:()V
  #453 = NameAndType        #225:#220     // preserve:Z
  #454 = NameAndType        #310:#281     // postIterationCleanup:(Ljava/lang/String;)V
  #455 = Utf8               startIteration()
  #456 = NameAndType        #640:#281     // println:(Ljava/lang/String;)V
  #457 = Utf8               org/dacapo/harness/Benchmark
  #458 = Utf8               dacapo.timeout.dialation
  #459 = NameAndType        #229:#218     // timeoutDialation:Ljava/lang/String;
  #460 = NameAndType        #641:#642     // clone:()Ljava/lang/Object;
  #461 = Utf8               java/util/Properties
  #462 = NameAndType        #289:#290     // augmentSystemProperties:(Ljava/util/Properties;)V
  #463 = NameAndType        #643:#290     // setProperties:(Ljava/util/Properties;)V
  #464 = NameAndType        #222:#220     // validateOutput:Z
  #465 = NameAndType        #644:#273     // version:()V
  #466 = NameAndType        #645:#273     // openLog:()V
  #467 = NameAndType        #294:#273     // useBenchmarkClassLoader:()V
  #468 = NameAndType        #295:#273     // revertClassLoader:()V
  #469 = NameAndType        #646:#273     // closeLog:()V
  #470 = Utf8               stopIteration()
  #471 = Class              #647          // java/lang/Thread
  #472 = NameAndType        #648:#649     // currentThread:()Ljava/lang/Thread;
  #473 = NameAndType        #650:#651     // getContextClassLoader:()Ljava/lang/ClassLoader;
  #474 = NameAndType        #239:#238     // savedClassLoader:Ljava/lang/ClassLoader;
  #475 = NameAndType        #652:#653     // setContextClassLoader:(Ljava/lang/ClassLoader;)V
  #476 = Utf8               validate(
  #477 = NameAndType        #224:#220     // validate:Z
  #478 = NameAndType        #619:#654     // append:(Z)Ljava/lang/StringBuilder;
  #479 = Utf8               )
  #480 = NameAndType        #228:#220     // validationReport:Z
  #481 = NameAndType        #226:#227     // valRepFile:Ljava/io/PrintWriter;
  #482 = Utf8               Validating
  #483 = NameAndType        #655:#656     // getOutputs:(Ljava/lang/String;)Ljava/util/Set;
  #484 = Class              #657          // java/util/Set
  #485 = NameAndType        #658:#659     // iterator:()Ljava/util/Iterator;
  #486 = Class              #600          // java/util/Iterator
  #487 = NameAndType        #660:#372     // hasNext:()Z
  #488 = NameAndType        #661:#642     // next:()Ljava/lang/Object;
  #489 = Utf8               java/lang/String
  #490 = NameAndType        #662:#663     // hasDigest:(Ljava/lang/String;Ljava/lang/String;)Z
  #491 = NameAndType        #664:#624     // getDigest:(Ljava/lang/String;Ljava/lang/String;)Ljava/lang/String;
  #492 = NameAndType        #665:#663     // isTextFile:(Ljava/lang/String;Ljava/lang/String;)Z
  #493 = NameAndType        #666:#663     // filterScratch:(Ljava/lang/String;Ljava/lang/String;)Z
  #494 = Class              #667          // org/dacapo/harness/FileDigest
  #495 = NameAndType        #668:#669     // get:(Ljava/lang/String;ZZLjava/io/File;)[B
  #496 = Class              #670          // org/dacapo/harness/Digest
  #497 = NameAndType        #621:#671     // toString:([B)Ljava/lang/String;
  #498 = Utf8               java/io/FileNotFoundException
  #499 = Utf8               <File not found>
  #500 = Utf8               java/io/IOException
  #501 = Utf8               <IO exception>
  #502 = NameAndType        #672:#273     // printStackTrace:()V
  #503 = Utf8                 \"
  #504 = Utf8               \" digest 0x
  #505 = Utf8               ,
  #506 = Utf8               $stdout
  #507 = NameAndType        #673:#674     // equals:(Ljava/lang/Object;)Z
  #508 = Utf8               $stderr
  #509 = Utf8               Digest validation failed for
  #510 = Utf8               , expecting 0x
  #511 = Utf8                found 0x
  #512 = Utf8               Digest validation succeeded for
  #513 = NameAndType        #675:#663     // hasLines:(Ljava/lang/String;Ljava/lang/String;)Z
  #514 = NameAndType        #676:#677     // getLines:(Ljava/lang/String;Ljava/lang/String;)I
  #515 = NameAndType        #358:#359     // lineCount:(Ljava/io/File;)I
  #516 = Utf8               File not found,
  #517 = Utf8               \" lines
  #518 = NameAndType        #619:#678     // append:(I)Ljava/lang/StringBuilder;
  #519 = Utf8               Line count validation failed for
  #520 = Utf8               , expecting
  #521 = Utf8                found
  #522 = Utf8               Line count validation succeeded for
  #523 = NameAndType        #679:#663     // hasBytes:(Ljava/lang/String;Ljava/lang/String;)Z
  #524 = NameAndType        #680:#681     // getBytes:(Ljava/lang/String;Ljava/lang/String;)J
  #525 = NameAndType        #363:#364     // byteCount:(Ljava/io/File;)J
  #526 = Utf8               \" bytes
  #527 = NameAndType        #619:#682     // append:(J)Ljava/lang/StringBuilder;
  #528 = Utf8               Byte count validation failed for
  #529 = Utf8               Byte count validation succeeded for
  #530 = NameAndType        #683:#663     // checkExists:(Ljava/lang/String;Ljava/lang/String;)Z
  #531 = Utf8               Expected file
  #532 = Utf8                does not exist
  #533 = Utf8               Existence validation succeeded for
  #534 = NameAndType        #684:#273     // flush:()V
  #535 = NameAndType        #685:#663     // isKept:(Ljava/lang/String;Ljava/lang/String;)Z
  #536 = NameAndType        #357:#352     // deleteFile:(Ljava/io/File;)V
  #537 = NameAndType        #351:#352     // deleteTree:(Ljava/io/File;)V
  #538 = Class              #686          // java/lang/Class
  #539 = NameAndType        #687:#651     // getClassLoader:()Ljava/lang/ClassLoader;
  #540 = Class              #601          // java/lang/ClassLoader
  #541 = NameAndType        #688:#313     // getResource:(Ljava/lang/String;)Ljava/net/URL;
  #542 = Utf8               Util.getURL: returns
  #543 = NameAndType        #689:#622     // getPath:()Ljava/lang/String;
  #544 = NameAndType        #312:#313     // getURL:(Ljava/lang/String;)Ljava/net/URL;
  #545 = Utf8               org/dacapo/harness/DacapoException
  #546 = Utf8               No such zip file: \"
  #547 = Utf8               \"
  #548 = Utf8               java/io/BufferedInputStream
  #549 = Class              #602          // java/net/URL
  #550 = NameAndType        #690:#691     // openStream:()Ljava/io/InputStream;
  #551 = NameAndType        #269:#692     // "<init>":(Ljava/io/InputStream;)V
  #552 = NameAndType        #329:#330     // unpackZipStream:(Ljava/io/BufferedInputStream;Ljava/io/File;)V
  #553 = Utf8               Extracting file
  #554 = Utf8                into
  #555 = NameAndType        #693:#622     // getCanonicalPath:()Ljava/lang/String;
  #556 = Utf8               No such file: \"
  #557 = NameAndType        #337:#338     // fileFromInputStream:(Ljava/io/InputStream;Ljava/io/File;)V
  #558 = Utf8               java/util/zip/ZipInputStream
  #559 = NameAndType        #694:#695     // getNextEntry:()Ljava/util/zip/ZipEntry;
  #560 = Utf8               Unpacking
  #561 = Class              #603          // java/util/zip/ZipEntry
  #562 = NameAndType        #696:#622     // getName:()Ljava/lang/String;
  #563 = NameAndType        #697:#372     // isDirectory:()Z
  #564 = NameAndType        #698:#273     // close:()V
  #565 = Utf8               java/io/FileOutputStream
  #566 = NameAndType        #269:#352     // "<init>":(Ljava/io/File;)V
  #567 = Utf8               java/io/BufferedOutputStream
  #568 = NameAndType        #269:#699     // "<init>":(Ljava/io/OutputStream;I)V
  #569 = Class              #604          // java/io/InputStream
  #570 = NameAndType        #700:#701     // read:([BII)I
  #571 = NameAndType        #702:#703     // write:([BII)V
  #572 = Utf8               Deleting
  #573 = NameAndType        #704:#372     // delete:()Z
  #574 = NameAndType        #705:#706     // listFiles:()[Ljava/io/File;
  #575 = Utf8               java/io/BufferedReader
  #576 = Utf8               java/io/FileReader
  #577 = NameAndType        #269:#707     // "<init>":(Ljava/io/Reader;)V
  #578 = NameAndType        #708:#622     // readLine:()Ljava/lang/String;
  #579 = NameAndType        #709:#612     // length:()J
  #580 = Class              #710          // org/dacapo/harness/CommandLineArgs
  #581 = NameAndType        #378:#372     // getSilent:()Z
  #582 = NameAndType        #375:#372     // getPreserve:()Z
  #583 = NameAndType        #374:#372     // getValidate:()Z
  #584 = NameAndType        #373:#372     // getValidateOutput:()Z
  #585 = NameAndType        #711:#372     // getPreIterationGC:()Z
  #586 = NameAndType        #712:#622     // getTimeoutDialation:()Ljava/lang/String;
  #587 = NameAndType        #713:#622     // getValidationReport:()Ljava/lang/String;
  #588 = NameAndType        #369:#281     // enableValidationReport:(Ljava/lang/String;)V
  #589 = Utf8               java/io/PrintWriter
  #590 = Utf8               java/io/BufferedWriter
  #591 = Utf8               java/io/FileWriter
  #592 = NameAndType        #269:#616     // "<init>":(Ljava/lang/String;Z)V
  #593 = NameAndType        #269:#714     // "<init>":(Ljava/io/Writer;)V
  #594 = NameAndType        #715:#716     // exit:(I)V
  #595 = Utf8               1
  #596 = Utf8               java/lang/Object
  #597 = Utf8               org/dacapo/harness/Callback
  #598 = Utf8               java/lang/Throwable
  #599 = Utf8               java/lang/Exception
  #600 = Utf8               java/util/Iterator
  #601 = Utf8               java/lang/ClassLoader
  #602 = Utf8               java/net/URL
  #603 = Utf8               java/util/zip/ZipEntry
  #604 = Utf8               java/io/InputStream
  #605 = Utf8               java/lang/System
  #606 = Utf8               setOut
  #607 = Utf8               (Ljava/io/PrintStream;)V
  #608 = Utf8               setErr
  #609 = Utf8               gc
  #610 = Utf8               org/dacapo/parser/Config
  #611 = Utf8               currentTimeMillis
  #612 = Utf8               ()J
  #613 = Utf8               stop
  #614 = Utf8               (J)V
  #615 = Utf8               complete
  #616 = Utf8               (Ljava/lang/String;Z)V
  #617 = Utf8               getProperties
  #618 = Utf8               ()Ljava/util/Properties;
  #619 = Utf8               append
  #620 = Utf8               (Ljava/lang/String;)Ljava/lang/StringBuilder;
  #621 = Utf8               toString
  #622 = Utf8               ()Ljava/lang/String;
  #623 = Utf8               setProperty
  #624 = Utf8               (Ljava/lang/String;Ljava/lang/String;)Ljava/lang/String;
  #625 = Utf8               (Ljava/io/File;Ljava/lang/String;)V
  #626 = Utf8               (Ljava/io/OutputStream;Ljava/io/File;)V
  #627 = Utf8               enableOutput
  #628 = Utf8               (Z)V
  #629 = Utf8               org/dacapo/harness/DacapoClassLoader
  #630 = Utf8               create
  #631 = Utf8               (Lorg/dacapo/parser/Config;Ljava/io/File;)Lorg/dacapo/harness/DacapoClassLoader;
  #632 = Utf8               (Ljava/lang/Object;)Ljava/lang/StringBuilder;
  #633 = Utf8               exists
  #634 = Utf8               mkdir
  #635 = Utf8               jars
  #636 = Utf8               preprocessArgs
  #637 = Utf8               (Ljava/lang/String;Ljava/io/File;)[Ljava/lang/String;
  #638 = Utf8               java/io/PrintStream
  #639 = Utf8               print
  #640 = Utf8               println
  #641 = Utf8               clone
  #642 = Utf8               ()Ljava/lang/Object;
  #643 = Utf8               setProperties
  #644 = Utf8               version
  #645 = Utf8               openLog
  #646 = Utf8               closeLog
  #647 = Utf8               java/lang/Thread
  #648 = Utf8               currentThread
  #649 = Utf8               ()Ljava/lang/Thread;
  #650 = Utf8               getContextClassLoader
  #651 = Utf8               ()Ljava/lang/ClassLoader;
  #652 = Utf8               setContextClassLoader
  #653 = Utf8               (Ljava/lang/ClassLoader;)V
  #654 = Utf8               (Z)Ljava/lang/StringBuilder;
  #655 = Utf8               getOutputs
  #656 = Utf8               (Ljava/lang/String;)Ljava/util/Set;
  #657 = Utf8               java/util/Set
  #658 = Utf8               iterator
  #659 = Utf8               ()Ljava/util/Iterator;
  #660 = Utf8               hasNext
  #661 = Utf8               next
  #662 = Utf8               hasDigest
  #663 = Utf8               (Ljava/lang/String;Ljava/lang/String;)Z
  #664 = Utf8               getDigest
  #665 = Utf8               isTextFile
  #666 = Utf8               filterScratch
  #667 = Utf8               org/dacapo/harness/FileDigest
  #668 = Utf8               get
  #669 = Utf8               (Ljava/lang/String;ZZLjava/io/File;)[B
  #670 = Utf8               org/dacapo/harness/Digest
  #671 = Utf8               ([B)Ljava/lang/String;
  #672 = Utf8               printStackTrace
  #673 = Utf8               equals
  #674 = Utf8               (Ljava/lang/Object;)Z
  #675 = Utf8               hasLines
  #676 = Utf8               getLines
  #677 = Utf8               (Ljava/lang/String;Ljava/lang/String;)I
  #678 = Utf8               (I)Ljava/lang/StringBuilder;
  #679 = Utf8               hasBytes
  #680 = Utf8               getBytes
  #681 = Utf8               (Ljava/lang/String;Ljava/lang/String;)J
  #682 = Utf8               (J)Ljava/lang/StringBuilder;
  #683 = Utf8               checkExists
  #684 = Utf8               flush
  #685 = Utf8               isKept
  #686 = Utf8               java/lang/Class
  #687 = Utf8               getClassLoader
  #688 = Utf8               getResource
  #689 = Utf8               getPath
  #690 = Utf8               openStream
  #691 = Utf8               ()Ljava/io/InputStream;
  #692 = Utf8               (Ljava/io/InputStream;)V
  #693 = Utf8               getCanonicalPath
  #694 = Utf8               getNextEntry
  #695 = Utf8               ()Ljava/util/zip/ZipEntry;
  #696 = Utf8               getName
  #697 = Utf8               isDirectory
  #698 = Utf8               close
  #699 = Utf8               (Ljava/io/OutputStream;I)V
  #700 = Utf8               read
  #701 = Utf8               ([BII)I
  #702 = Utf8               write
  #703 = Utf8               ([BII)V
  #704 = Utf8               delete
  #705 = Utf8               listFiles
  #706 = Utf8               ()[Ljava/io/File;
  #707 = Utf8               (Ljava/io/Reader;)V
  #708 = Utf8               readLine
  #709 = Utf8               length
  #710 = Utf8               org/dacapo/harness/CommandLineArgs
  #711 = Utf8               getPreIterationGC
  #712 = Utf8               getTimeoutDialation
  #713 = Utf8               getValidationReport
  #714 = Utf8               (Ljava/io/Writer;)V
  #715 = Utf8               exit
  #716 = Utf8               (I)V
{
  protected final java.io.File scratch;
    descriptor: Ljava/io/File;
    flags: (0x0014) ACC_PROTECTED, ACC_FINAL

  protected final org.dacapo.parser.Config config;
    descriptor: Lorg/dacapo/parser/Config;
    flags: (0x0014) ACC_PROTECTED, ACC_FINAL

  protected java.lang.ClassLoader loader;
    descriptor: Ljava/lang/ClassLoader;
    flags: (0x0004) ACC_PROTECTED

  protected int iteration;
    descriptor: I
    flags: (0x0004) ACC_PROTECTED

  protected java.lang.reflect.Method method;
    descriptor: Ljava/lang/reflect/Method;
    flags: (0x0004) ACC_PROTECTED

  public final boolean run(org.dacapo.harness.Callback, java.lang.String) throws java.lang.Exception;
    descriptor: (Lorg/dacapo/harness/Callback;Ljava/lang/String;)Z
    flags: (0x0011) ACC_PUBLIC, ACC_FINAL
    Code:
      stack=4, locals=8, args_size=3
         0: aload_0
         1: dup
         2: getfield      #1                  // Field iteration:I
         5: iconst_1
         6: iadd
         7: putfield      #1                  // Field iteration:I
        10: aload_0
        11: getfield      #1                  // Field iteration:I
        14: iconst_1
        15: if_icmpne     35
        18: aload_0
        19: aload_2
        20: invokevirtual #2                  // Method prepare:(Ljava/lang/String;)V
        23: getstatic     #3                  // Field savedOut:Ljava/io/PrintStream;
        26: invokestatic  #4                  // Method java/lang/System.setOut:(Ljava/io/PrintStream;)V
        29: getstatic     #5                  // Field savedErr:Ljava/io/PrintStream;
        32: invokestatic  #6                  // Method java/lang/System.setErr:(Ljava/io/PrintStream;)V
        35: aload_0
        36: aload_2
        37: invokevirtual #7                  // Method preIteration:(Ljava/lang/String;)V
        40: getstatic     #3                  // Field savedOut:Ljava/io/PrintStream;
        43: invokestatic  #4                  // Method java/lang/System.setOut:(Ljava/io/PrintStream;)V
        46: getstatic     #5                  // Field savedErr:Ljava/io/PrintStream;
        49: invokestatic  #6                  // Method java/lang/System.setErr:(Ljava/io/PrintStream;)V
        52: getstatic     #8                  // Field preIterationGC:Z
        55: ifeq          61
        58: invokestatic  #9                  // Method java/lang/System.gc:()V
        61: aload_1
        62: aload_0
        63: getfield      #10                 // Field config:Lorg/dacapo/parser/Config;
        66: getfield      #11                 // Field org/dacapo/parser/Config.name:Ljava/lang/String;
        69: invokevirtual #12                 // Method org/dacapo/harness/Callback.start:(Ljava/lang/String;)V
        72: invokestatic  #13                 // Method java/lang/System.currentTimeMillis:()J
        75: lstore_3
        76: aload_0
        77: invokevirtual #14                 // Method startIteration:()V
        80: aload_0
        81: aload_2
        82: invokevirtual #15                 // Method iterate:(Ljava/lang/String;)V
        85: aload_0
        86: invokevirtual #16                 // Method stopIteration:()V
        89: goto          101
        92: astore        5
        94: aload_0
        95: invokevirtual #16                 // Method stopIteration:()V
        98: aload         5
       100: athrow
       101: invokestatic  #13                 // Method java/lang/System.currentTimeMillis:()J
       104: lload_3
       105: lsub
       106: lstore        5
       108: aload_1
       109: lload         5
       111: invokevirtual #17                 // Method org/dacapo/harness/Callback.stop:(J)V
       114: aload_0
       115: aload_2
       116: invokevirtual #18                 // Method validate:(Ljava/lang/String;)Z
       119: istore        7
       121: aload_1
       122: aload_0
       123: getfield      #10                 // Field config:Lorg/dacapo/parser/Config;
       126: getfield      #11                 // Field org/dacapo/parser/Config.name:Ljava/lang/String;
       129: iload         7
       131: invokevirtual #19                 // Method org/dacapo/harness/Callback.complete:(Ljava/lang/String;Z)V
       134: aload_0
       135: aload_2
       136: invokevirtual #20                 // Method postIteration:(Ljava/lang/String;)V
       139: iload         7
       141: ireturn
      Exception table:
         from    to  target type
            80    85    92   any
            92    94    92   any
      LineNumberTable:
        line 161: 0
        line 162: 10
        line 163: 18
        line 167: 23
        line 168: 29
        line 171: 35
        line 174: 40
        line 175: 46
        line 177: 52
        line 178: 58
        line 181: 61
        line 183: 72
        line 185: 76
        line 187: 80
        line 189: 85
        line 190: 89
        line 189: 92
        line 192: 101
        line 194: 108
        line 196: 114
        line 197: 121
        line 198: 134
        line 199: 139
      LocalVariableTable:
        Start  Length  Slot  Name   Signature
            0     142     0  this   Lorg/dacapo/harness/Benchmark;
            0     142     1 callback   Lorg/dacapo/harness/Callback;
            0     142     2  size   Ljava/lang/String;
           76      66     3 start   J
          108      34     5 duration   J
          121      21     7 valid   Z
      StackMapTable: number_of_entries = 4
        frame_type = 35 /* same */
        frame_type = 25 /* same */
        frame_type = 255 /* full_frame */
          offset_delta = 30
          locals = [ class org/dacapo/harness/Benchmark, class org/dacapo/harness/Callback, class java/lang/String, long ]
          stack = [ class java/lang/Throwable ]
        frame_type = 8 /* same */
    Exceptions:
      throws java.lang.Exception

  public org.dacapo.harness.Benchmark(org.dacapo.parser.Config, java.io.File) throws java.lang.Exception;
    descriptor: (Lorg/dacapo/parser/Config;Ljava/io/File;)V
    flags: (0x0001) ACC_PUBLIC
    Code:
      stack=4, locals=3, args_size=3
         0: aload_0
         1: aload_1
         2: aload_2
         3: iconst_1
         4: invokespecial #21                 // Method "<init>":(Lorg/dacapo/parser/Config;Ljava/io/File;Z)V
         7: return
      LineNumberTable:
        line 209: 0
        line 210: 7
      LocalVariableTable:
        Start  Length  Slot  Name   Signature
            0       8     0  this   Lorg/dacapo/harness/Benchmark;
            0       8     1 config   Lorg/dacapo/parser/Config;
            0       8     2 scratch   Ljava/io/File;
    Exceptions:
      throws java.lang.Exception

  public org.dacapo.harness.Benchmark(org.dacapo.parser.Config, java.io.File, boolean) throws java.lang.Exception;
    descriptor: (Lorg/dacapo/parser/Config;Ljava/io/File;Z)V
    flags: (0x0001) ACC_PUBLIC
    Code:
      stack=2, locals=4, args_size=4
         0: aload_0
         1: invokespecial #22                 // Method java/lang/Object."<init>":()V
         4: aload_0
         5: iconst_0
         6: putfield      #1                  // Field iteration:I
         9: iload_3
        10: putstatic     #23                 // Field silent:Z
        13: aload_0
        14: aload_2
        15: putfield      #24                 // Field scratch:Ljava/io/File;
        18: aload_0
        19: aload_1
        20: putfield      #10                 // Field config:Lorg/dacapo/parser/Config;
        23: aload_0
        24: invokespecial #25                 // Method initialize:()V
        27: return
      LineNumberTable:
        line 212: 0
        line 146: 4
        line 214: 9
        line 215: 13
        line 216: 18
        line 217: 23
        line 218: 27
      LocalVariableTable:
        Start  Length  Slot  Name   Signature
            0      28     0  this   Lorg/dacapo/harness/Benchmark;
            0      28     1 config   Lorg/dacapo/parser/Config;
            0      28     2 scratch   Ljava/io/File;
            0      28     3 silent   Z
    Exceptions:
      throws java.lang.Exception

  protected void prepare() throws java.lang.Exception;
    descriptor: ()V
    flags: (0x0004) ACC_PROTECTED
    Code:
      stack=2, locals=1, args_size=1
         0: new           #29                 // class java/lang/StringBuilder
         3: dup
         4: invokespecial #30                 // Method java/lang/StringBuilder."<init>":()V
         7: ldc           #59                 // String dat/
         9: invokevirtual #31                 // Method java/lang/StringBuilder.append:(Ljava/lang/String;)Ljava/lang/StringBuilder;
        12: aload_0
        13: getfield      #10                 // Field config:Lorg/dacapo/parser/Config;
        16: getfield      #11                 // Field org/dacapo/parser/Config.name:Ljava/lang/String;
        19: invokevirtual #31                 // Method java/lang/StringBuilder.append:(Ljava/lang/String;)Ljava/lang/StringBuilder;
        22: ldc           #60                 // String .zip
        24: invokevirtual #31                 // Method java/lang/StringBuilder.append:(Ljava/lang/String;)Ljava/lang/StringBuilder;
        27: invokevirtual #33                 // Method java/lang/StringBuilder.toString:()Ljava/lang/String;
        30: aload_0
        31: getfield      #24                 // Field scratch:Ljava/io/File;
        34: invokestatic  #61                 // Method unpackZipFileResource:(Ljava/lang/String;Ljava/io/File;)V
        37: return
      LineNumberTable:
        line 262: 0
        line 263: 37
      LocalVariableTable:
        Start  Length  Slot  Name   Signature
            0      38     0  this   Lorg/dacapo/harness/Benchmark;
    Exceptions:
      throws java.lang.Exception

  protected void prepare(java.lang.String) throws java.lang.Exception;
    descriptor: (Ljava/lang/String;)V
    flags: (0x0004) ACC_PROTECTED
    Code:
      stack=0, locals=2, args_size=2
         0: return
      LineNumberTable:
        line 273: 0
      LocalVariableTable:
        Start  Length  Slot  Name   Signature
            0       1     0  this   Lorg/dacapo/harness/Benchmark;
            0       1     1  size   Ljava/lang/String;
    Exceptions:
      throws java.lang.Exception

  public void preIteration(java.lang.String) throws java.lang.Exception;
    descriptor: (Ljava/lang/String;)V
    flags: (0x0001) ACC_PUBLIC
    Code:
      stack=4, locals=4, args_size=2
         0: getstatic     #62                 // Field verbose:Z
         3: ifeq          74
         6: aload_0
         7: getfield      #10                 // Field config:Lorg/dacapo/parser/Config;
        10: aload_1
        11: aload_0
        12: getfield      #24                 // Field scratch:Ljava/io/File;
        15: invokevirtual #63                 // Method org/dacapo/parser/Config.preprocessArgs:(Ljava/lang/String;Ljava/io/File;)[Ljava/lang/String;
        18: astore_2
        19: getstatic     #36                 // Field java/lang/System.out:Ljava/io/PrintStream;
        22: ldc           #64                 // String Benchmark parameters:
        24: invokevirtual #65                 // Method java/io/PrintStream.print:(Ljava/lang/String;)V
        27: iconst_0
        28: istore_3
        29: iload_3
        30: aload_2
        31: arraylength
        32: if_icmpge     68
        35: getstatic     #36                 // Field java/lang/System.out:Ljava/io/PrintStream;
        38: new           #29                 // class java/lang/StringBuilder
        41: dup
        42: invokespecial #30                 // Method java/lang/StringBuilder."<init>":()V
        45: aload_2
        46: iload_3
        47: aaload
        48: invokevirtual #31                 // Method java/lang/StringBuilder.append:(Ljava/lang/String;)Ljava/lang/StringBuilder;
        51: ldc           #66                 // String
        53: invokevirtual #31                 // Method java/lang/StringBuilder.append:(Ljava/lang/String;)Ljava/lang/StringBuilder;
        56: invokevirtual #33                 // Method java/lang/StringBuilder.toString:()Ljava/lang/String;
        59: invokevirtual #65                 // Method java/io/PrintStream.print:(Ljava/lang/String;)V
        62: iinc          3, 1
        65: goto          29
        68: getstatic     #36                 // Field java/lang/System.out:Ljava/io/PrintStream;
        71: invokevirtual #67                 // Method java/io/PrintStream.println:()V
        74: getstatic     #68                 // Field preserve:Z
        77: ifeq          93
        80: aload_0
        81: getfield      #1                  // Field iteration:I
        84: iconst_1
        85: if_icmple     93
        88: aload_0
        89: aload_1
        90: invokevirtual #69                 // Method postIterationCleanup:(Ljava/lang/String;)V
        93: return
      LineNumberTable:
        line 284: 0
        line 285: 6
        line 286: 19
        line 287: 27
        line 288: 35
        line 287: 62
        line 289: 68
        line 296: 74
        line 297: 88
        line 298: 93
      LocalVariableTable:
        Start  Length  Slot  Name   Signature
           29      39     3     i   I
           19      55     2  args   [Ljava/lang/String;
            0      94     0  this   Lorg/dacapo/harness/Benchmark;
            0      94     1  size   Ljava/lang/String;
      StackMapTable: number_of_entries = 4
        frame_type = 253 /* append */
          offset_delta = 29
          locals = [ class "[Ljava/lang/String;", int ]
        frame_type = 250 /* chop */
          offset_delta = 38
        frame_type = 250 /* chop */
          offset_delta = 5
        frame_type = 18 /* same */
    Exceptions:
      throws java.lang.Exception

  public final void startIteration();
    descriptor: ()V
    flags: (0x0011) ACC_PUBLIC, ACC_FINAL
    Code:
      stack=2, locals=2, args_size=1
         0: getstatic     #62                 // Field verbose:Z
         3: ifeq          14
         6: getstatic     #36                 // Field java/lang/System.out:Ljava/io/PrintStream;
         9: ldc           #70                 // String startIteration()
        11: invokevirtual #71                 // Method java/io/PrintStream.println:(Ljava/lang/String;)V
        14: ldc           #73                 // String dacapo.timeout.dialation
        16: getstatic     #74                 // Field timeoutDialation:Ljava/lang/String;
        19: invokestatic  #35                 // Method java/lang/System.setProperty:(Ljava/lang/String;Ljava/lang/String;)Ljava/lang/String;
        22: pop
        23: aload_0
        24: getfield      #27                 // Field savedSystemProperties:Ljava/util/Properties;
        27: invokevirtual #75                 // Method java/util/Properties.clone:()Ljava/lang/Object;
        30: checkcast     #76                 // class java/util/Properties
        33: astore_1
        34: aload_0
        35: aload_1
        36: invokevirtual #77                 // Method augmentSystemProperties:(Ljava/util/Properties;)V
        39: aload_1
        40: invokestatic  #78                 // Method java/lang/System.setProperties:(Ljava/util/Properties;)V
        43: getstatic     #79                 // Field validateOutput:Z
        46: ifeq          93
        49: getstatic     #37                 // Field out:Lorg/dacapo/harness/TeePrintStream;
        52: invokestatic  #4                  // Method java/lang/System.setOut:(Ljava/io/PrintStream;)V
        55: getstatic     #45                 // Field err:Lorg/dacapo/harness/TeePrintStream;
        58: invokestatic  #6                  // Method java/lang/System.setErr:(Ljava/io/PrintStream;)V
        61: aload_0
        62: getfield      #1                  // Field iteration:I
        65: iconst_1
        66: if_icmple     81
        69: getstatic     #37                 // Field out:Lorg/dacapo/harness/TeePrintStream;
        72: invokevirtual #80                 // Method org/dacapo/harness/TeePrintStream.version:()V
        75: getstatic     #45                 // Field err:Lorg/dacapo/harness/TeePrintStream;
        78: invokevirtual #80                 // Method org/dacapo/harness/TeePrintStream.version:()V
        81: getstatic     #37                 // Field out:Lorg/dacapo/harness/TeePrintStream;
        84: invokevirtual #81                 // Method org/dacapo/harness/TeePrintStream.openLog:()V
        87: getstatic     #45                 // Field err:Lorg/dacapo/harness/TeePrintStream;
        90: invokevirtual #81                 // Method org/dacapo/harness/TeePrintStream.openLog:()V
        93: aload_0
        94: invokevirtual #82                 // Method useBenchmarkClassLoader:()V
        97: return
      LineNumberTable:
        line 306: 0
        line 307: 6
        line 309: 14
        line 311: 23
        line 312: 34
        line 313: 39
        line 315: 43
        line 316: 49
        line 317: 55
        line 318: 61
        line 319: 69
        line 320: 75
        line 322: 81
        line 323: 87
        line 325: 93
        line 326: 97
      LocalVariableTable:
        Start  Length  Slot  Name   Signature
            0      98     0  this   Lorg/dacapo/harness/Benchmark;
           34      64     1 augmentedSystemProperties   Ljava/util/Properties;
      StackMapTable: number_of_entries = 3
        frame_type = 14 /* same */
        frame_type = 252 /* append */
          offset_delta = 66
          locals = [ class java/util/Properties ]
        frame_type = 11 /* same */

  public void augmentSystemProperties(java.util.Properties);
    descriptor: (Ljava/util/Properties;)V
    flags: (0x0001) ACC_PUBLIC
    Code:
      stack=0, locals=2, args_size=2
         0: return
      LineNumberTable:
        line 335: 0
      LocalVariableTable:
        Start  Length  Slot  Name   Signature
            0       1     0  this   Lorg/dacapo/harness/Benchmark;
            0       1     1 systemProperties   Ljava/util/Properties;

  public abstract void iterate(java.lang.String) throws java.lang.Exception;
    descriptor: (Ljava/lang/String;)V
    flags: (0x0401) ACC_PUBLIC, ACC_ABSTRACT
    Exceptions:
      throws java.lang.Exception

  public final void stopIteration();
    descriptor: ()V
    flags: (0x0011) ACC_PUBLIC, ACC_FINAL
    Code:
      stack=2, locals=1, args_size=1
         0: aload_0
         1: invokevirtual #83                 // Method revertClassLoader:()V
         4: getstatic     #79                 // Field validateOutput:Z
         7: ifeq          34
        10: getstatic     #37                 // Field out:Lorg/dacapo/harness/TeePrintStream;
        13: invokevirtual #84                 // Method org/dacapo/harness/TeePrintStream.closeLog:()V
        16: getstatic     #45                 // Field err:Lorg/dacapo/harness/TeePrintStream;
        19: invokevirtual #84                 // Method org/dacapo/harness/TeePrintStream.closeLog:()V
        22: getstatic     #3                  // Field savedOut:Ljava/io/PrintStream;
        25: invokestatic  #4                  // Method java/lang/System.setOut:(Ljava/io/PrintStream;)V
        28: getstatic     #5                  // Field savedErr:Ljava/io/PrintStream;
        31: invokestatic  #6                  // Method java/lang/System.setErr:(Ljava/io/PrintStream;)V
        34: aload_0
        35: getfield      #27                 // Field savedSystemProperties:Ljava/util/Properties;
        38: invokestatic  #78                 // Method java/lang/System.setProperties:(Ljava/util/Properties;)V
        41: getstatic     #62                 // Field verbose:Z
        44: ifeq          55
        47: getstatic     #36                 // Field java/lang/System.out:Ljava/io/PrintStream;
        50: ldc           #85                 // String stopIteration()
        52: invokevirtual #71                 // Method java/io/PrintStream.println:(Ljava/lang/String;)V
        55: return
      LineNumberTable:
        line 350: 0
        line 351: 4
        line 352: 10
        line 353: 16
        line 354: 22
        line 355: 28
        line 358: 34
        line 360: 41
        line 361: 47
        line 363: 55
      LocalVariableTable:
        Start  Length  Slot  Name   Signature
            0      56     0  this   Lorg/dacapo/harness/Benchmark;
      StackMapTable: number_of_entries = 2
        frame_type = 34 /* same */
        frame_type = 20 /* same */

  protected void useBenchmarkClassLoader();
    descriptor: ()V
    flags: (0x0004) ACC_PROTECTED
    Code:
      stack=2, locals=1, args_size=1
         0: aload_0
         1: getfield      #49                 // Field loader:Ljava/lang/ClassLoader;
         4: ifnull        27
         7: aload_0
         8: invokestatic  #86                 // Method java/lang/Thread.currentThread:()Ljava/lang/Thread;
        11: invokevirtual #87                 // Method java/lang/Thread.getContextClassLoader:()Ljava/lang/ClassLoader;
        14: putfield      #88                 // Field savedClassLoader:Ljava/lang/ClassLoader;
        17: invokestatic  #86                 // Method java/lang/Thread.currentThread:()Ljava/lang/Thread;
        20: aload_0
        21: getfield      #49                 // Field loader:Ljava/lang/ClassLoader;
        24: invokevirtual #89                 // Method java/lang/Thread.setContextClassLoader:(Ljava/lang/ClassLoader;)V
        27: return
      LineNumberTable:
        line 369: 0
        line 370: 7
        line 371: 17
        line 373: 27
      LocalVariableTable:
        Start  Length  Slot  Name   Signature
            0      28     0  this   Lorg/dacapo/harness/Benchmark;
      StackMapTable: number_of_entries = 1
        frame_type = 27 /* same */

  protected void revertClassLoader();
    descriptor: ()V
    flags: (0x0004) ACC_PROTECTED
    Code:
      stack=2, locals=1, args_size=1
         0: aload_0
         1: getfield      #49                 // Field loader:Ljava/lang/ClassLoader;
         4: ifnull        17
         7: invokestatic  #86                 // Method java/lang/Thread.currentThread:()Ljava/lang/Thread;
        10: aload_0
        11: getfield      #88                 // Field savedClassLoader:Ljava/lang/ClassLoader;
        14: invokevirtual #89                 // Method java/lang/Thread.setContextClassLoader:(Ljava/lang/ClassLoader;)V
        17: return
      LineNumberTable:
        line 379: 0
        line 380: 7
        line 382: 17
      LocalVariableTable:
        Start  Length  Slot  Name   Signature
            0      18     0  this   Lorg/dacapo/harness/Benchmark;
      StackMapTable: number_of_entries = 1
        frame_type = 17 /* same */

  public boolean validate(java.lang.String);
    descriptor: (Ljava/lang/String;)Z
    flags: (0x0001) ACC_PUBLIC
    Code:
      stack=5, locals=10, args_size=2
         0: getstatic     #62                 // Field verbose:Z
         3: ifeq          38
         6: getstatic     #36                 // Field java/lang/System.out:Ljava/io/PrintStream;
         9: new           #29                 // class java/lang/StringBuilder
        12: dup
        13: invokespecial #30                 // Method java/lang/StringBuilder."<init>":()V
        16: ldc           #90                 // String validate(
        18: invokevirtual #31                 // Method java/lang/StringBuilder.append:(Ljava/lang/String;)Ljava/lang/StringBuilder;
        21: getstatic     #91                 // Field validate:Z
        24: invokevirtual #92                 // Method java/lang/StringBuilder.append:(Z)Ljava/lang/StringBuilder;
        27: ldc           #93                 // String )
        29: invokevirtual #31                 // Method java/lang/StringBuilder.append:(Ljava/lang/String;)Ljava/lang/StringBuilder;
        32: invokevirtual #33                 // Method java/lang/StringBuilder.toString:()Ljava/lang/String;
        35: invokevirtual #71                 // Method java/io/PrintStream.println:(Ljava/lang/String;)V
        38: getstatic     #91                 // Field validate:Z
        41: ifne          46
        44: iconst_1
        45: ireturn
        46: getstatic     #94                 // Field validationReport:Z
        49: ifeq          92
        52: getstatic     #95                 // Field valRepFile:Ljava/io/PrintWriter;
        55: new           #29                 // class java/lang/StringBuilder
        58: dup
        59: invokespecial #30                 // Method java/lang/StringBuilder."<init>":()V
        62: ldc           #96                 // String Validating
        64: invokevirtual #31                 // Method java/lang/StringBuilder.append:(Ljava/lang/String;)Ljava/lang/StringBuilder;
        67: aload_0
        68: getfield      #10                 // Field config:Lorg/dacapo/parser/Config;
        71: getfield      #11                 // Field org/dacapo/parser/Config.name:Ljava/lang/String;
        74: invokevirtual #31                 // Method java/lang/StringBuilder.append:(Ljava/lang/String;)Ljava/lang/StringBuilder;
        77: ldc           #66                 // String
        79: invokevirtual #31                 // Method java/lang/StringBuilder.append:(Ljava/lang/String;)Ljava/lang/StringBuilder;
        82: aload_1
        83: invokevirtual #31                 // Method java/lang/StringBuilder.append:(Ljava/lang/String;)Ljava/lang/StringBuilder;
        86: invokevirtual #33                 // Method java/lang/StringBuilder.toString:()Ljava/lang/String;
        89: invokevirtual #97                 // Method java/io/PrintWriter.println:(Ljava/lang/String;)V
        92: iconst_1
        93: istore_2
        94: aload_0
        95: getfield      #10                 // Field config:Lorg/dacapo/parser/Config;
        98: aload_1
        99: invokevirtual #98                 // Method org/dacapo/parser/Config.getOutputs:(Ljava/lang/String;)Ljava/util/Set;
       102: invokeinterface #99,  1           // InterfaceMethod java/util/Set.iterator:()Ljava/util/Iterator;
       107: astore_3
       108: aload_3
       109: invokeinterface #100,  1          // InterfaceMethod java/util/Iterator.hasNext:()Z
       114: ifeq          945
       117: aload_3
       118: invokeinterface #101,  1          // InterfaceMethod java/util/Iterator.next:()Ljava/lang/Object;
       123: checkcast     #102                // class java/lang/String
       126: astore        4
       128: aload_0
       129: getfield      #10                 // Field config:Lorg/dacapo/parser/Config;
       132: aload_1
       133: aload         4
       135: invokevirtual #103                // Method org/dacapo/parser/Config.hasDigest:(Ljava/lang/String;Ljava/lang/String;)Z
       138: ifeq          383
       141: aload_0
       142: getfield      #10                 // Field config:Lorg/dacapo/parser/Config;
       145: aload_1
       146: aload         4
       148: invokevirtual #104                // Method org/dacapo/parser/Config.getDigest:(Ljava/lang/String;Ljava/lang/String;)Ljava/lang/String;
       151: astore        5
       153: aload_0
       154: aload         4
       156: invokevirtual #34                 // Method fileInScratch:(Ljava/lang/String;)Ljava/lang/String;
       159: aload_0
       160: getfield      #10                 // Field config:Lorg/dacapo/parser/Config;
       163: aload_1
       164: aload         4
       166: invokevirtual #105                // Method org/dacapo/parser/Config.isTextFile:(Ljava/lang/String;Ljava/lang/String;)Z
       169: aload_0
       170: getfield      #10                 // Field config:Lorg/dacapo/parser/Config;
       173: aload_1
       174: aload         4
       176: invokevirtual #106                // Method org/dacapo/parser/Config.filterScratch:(Ljava/lang/String;Ljava/lang/String;)Z
       179: aload_0
       180: getfield      #24                 // Field scratch:Ljava/io/File;
       183: invokestatic  #107                // Method org/dacapo/harness/FileDigest.get:(Ljava/lang/String;ZZLjava/io/File;)[B
       186: invokestatic  #108                // Method org/dacapo/harness/Digest.toString:([B)Ljava/lang/String;
       189: astore        6
       191: goto          214
       194: astore        7
       196: ldc           #110                // String <File not found>
       198: astore        6
       200: goto          214
       203: astore        7
       205: ldc           #112                // String <IO exception>
       207: astore        6
       209: aload         7
       211: invokevirtual #113                // Method java/io/IOException.printStackTrace:()V
       214: getstatic     #94                 // Field validationReport:Z
       217: ifeq          261
       220: getstatic     #95                 // Field valRepFile:Ljava/io/PrintWriter;
       223: new           #29                 // class java/lang/StringBuilder
       226: dup
       227: invokespecial #30                 // Method java/lang/StringBuilder."<init>":()V
       230: ldc           #114                // String   \"
       232: invokevirtual #31                 // Method java/lang/StringBuilder.append:(Ljava/lang/String;)Ljava/lang/StringBuilder;
       235: aload         4
       237: invokevirtual #31                 // Method java/lang/StringBuilder.append:(Ljava/lang/String;)Ljava/lang/StringBuilder;
       240: ldc           #115                // String \" digest 0x
       242: invokevirtual #31                 // Method java/lang/StringBuilder.append:(Ljava/lang/String;)Ljava/lang/StringBuilder;
       245: aload         6
       247: invokevirtual #31                 // Method java/lang/StringBuilder.append:(Ljava/lang/String;)Ljava/lang/StringBuilder;
       250: ldc           #116                // String ,
       252: invokevirtual #31                 // Method java/lang/StringBuilder.append:(Ljava/lang/String;)Ljava/lang/StringBuilder;
       255: invokevirtual #33                 // Method java/lang/StringBuilder.toString:()Ljava/lang/String;
       258: invokevirtual #97                 // Method java/io/PrintWriter.println:(Ljava/lang/String;)V
       261: getstatic     #79                 // Field validateOutput:Z
       264: ifne          290
       267: aload         4
       269: ldc           #117                // String $stdout
       271: invokevirtual #118                // Method java/lang/String.equals:(Ljava/lang/Object;)Z
       274: ifne          383
       277: aload         4
       279: ldc           #119                // String $stderr
       281: invokevirtual #118                // Method java/lang/String.equals:(Ljava/lang/Object;)Z
       284: ifeq          290
       287: goto          383
       290: aload         6
       292: aload         5
       294: invokevirtual #118                // Method java/lang/String.equals:(Ljava/lang/Object;)Z
       297: ifne          351
       300: iconst_0
       301: istore_2
       302: getstatic     #44                 // Field java/lang/System.err:Ljava/io/PrintStream;
       305: new           #29                 // class java/lang/StringBuilder
       308: dup
       309: invokespecial #30                 // Method java/lang/StringBuilder."<init>":()V
       312: ldc           #120                // String Digest validation failed for
       314: invokevirtual #31                 // Method java/lang/StringBuilder.append:(Ljava/lang/String;)Ljava/lang/StringBuilder;
       317: aload         4
       319: invokevirtual #31                 // Method java/lang/StringBuilder.append:(Ljava/lang/String;)Ljava/lang/StringBuilder;
       322: ldc           #121                // String , expecting 0x
       324: invokevirtual #31                 // Method java/lang/StringBuilder.append:(Ljava/lang/String;)Ljava/lang/StringBuilder;
       327: aload         5
       329: invokevirtual #31                 // Method java/lang/StringBuilder.append:(Ljava/lang/String;)Ljava/lang/StringBuilder;
       332: ldc           #122                // String  found 0x
       334: invokevirtual #31                 // Method java/lang/StringBuilder.append:(Ljava/lang/String;)Ljava/lang/StringBuilder;
       337: aload         6
       339: invokevirtual #31                 // Method java/lang/StringBuilder.append:(Ljava/lang/String;)Ljava/lang/StringBuilder;
       342: invokevirtual #33                 // Method java/lang/StringBuilder.toString:()Ljava/lang/String;
       345: invokevirtual #71                 // Method java/io/PrintStream.println:(Ljava/lang/String;)V
       348: goto          383
       351: getstatic     #62                 // Field verbose:Z
       354: ifeq          383
       357: getstatic     #36                 // Field java/lang/System.out:Ljava/io/PrintStream;
       360: new           #29                 // class java/lang/StringBuilder
       363: dup
       364: invokespecial #30                 // Method java/lang/StringBuilder."<init>":()V
       367: ldc           #123                // String Digest validation succeeded for
       369: invokevirtual #31                 // Method java/lang/StringBuilder.append:(Ljava/lang/String;)Ljava/lang/StringBuilder;
       372: aload         4
       374: invokevirtual #31                 // Method java/lang/StringBuilder.append:(Ljava/lang/String;)Ljava/lang/StringBuilder;
       377: invokevirtual #33                 // Method java/lang/StringBuilder.toString:()Ljava/lang/String;
       380: invokevirtual #71                 // Method java/io/PrintStream.println:(Ljava/lang/String;)V
       383: aload_0
       384: getfield      #10                 // Field config:Lorg/dacapo/parser/Config;
       387: aload_1
       388: aload         4
       390: invokevirtual #124                // Method org/dacapo/parser/Config.hasLines:(Ljava/lang/String;Ljava/lang/String;)Z
       393: ifeq          610
       396: aload_0
       397: getfield      #10                 // Field config:Lorg/dacapo/parser/Config;
       400: aload_1
       401: aload         4
       403: invokevirtual #125                // Method org/dacapo/parser/Config.getLines:(Ljava/lang/String;Ljava/lang/String;)I
       406: istore        5
       408: new           #39                 // class java/io/File
       411: dup
       412: aload_0
       413: getfield      #24                 // Field scratch:Ljava/io/File;
       416: aload         4
       418: invokespecial #41                 // Method java/io/File."<init>":(Ljava/io/File;Ljava/lang/String;)V
       421: invokestatic  #126                // Method lineCount:(Ljava/io/File;)I
       424: istore        6
       426: goto          473
       429: astore        7
       431: getstatic     #44                 // Field java/lang/System.err:Ljava/io/PrintStream;
       434: new           #29                 // class java/lang/StringBuilder
       437: dup
       438: invokespecial #30                 // Method java/lang/StringBuilder."<init>":()V
       441: ldc           #127                // String File not found,
       443: invokevirtual #31                 // Method java/lang/StringBuilder.append:(Ljava/lang/String;)Ljava/lang/StringBuilder;
       446: aload         4
       448: invokevirtual #31                 // Method java/lang/StringBuilder.append:(Ljava/lang/String;)Ljava/lang/StringBuilder;
       451: invokevirtual #33                 // Method java/lang/StringBuilder.toString:()Ljava/lang/String;
       454: invokevirtual #71                 // Method java/io/PrintStream.println:(Ljava/lang/String;)V
       457: iconst_m1
       458: istore        6
       460: goto          473
       463: astore        7
       465: aload         7
       467: invokevirtual #113                // Method java/io/IOException.printStackTrace:()V
       470: iconst_m1
       471: istore        6
       473: getstatic     #94                 // Field validationReport:Z
       476: ifeq          520
       479: getstatic     #95                 // Field valRepFile:Ljava/io/PrintWriter;
       482: new           #29                 // class java/lang/StringBuilder
       485: dup
       486: invokespecial #30                 // Method java/lang/StringBuilder."<init>":()V
       489: ldc           #114                // String   \"
       491: invokevirtual #31                 // Method java/lang/StringBuilder.append:(Ljava/lang/String;)Ljava/lang/StringBuilder;
       494: aload         4
       496: invokevirtual #31                 // Method java/lang/StringBuilder.append:(Ljava/lang/String;)Ljava/lang/StringBuilder;
       499: ldc           #128                // String \" lines
       501: invokevirtual #31                 // Method java/lang/StringBuilder.append:(Ljava/lang/String;)Ljava/lang/StringBuilder;
       504: iload         6
       506: invokevirtual #129                // Method java/lang/StringBuilder.append:(I)Ljava/lang/StringBuilder;
       509: ldc           #116                // String ,
       511: invokevirtual #31                 // Method java/lang/StringBuilder.append:(Ljava/lang/String;)Ljava/lang/StringBuilder;
       514: invokevirtual #33                 // Method java/lang/StringBuilder.toString:()Ljava/lang/String;
       517: invokevirtual #97                 // Method java/io/PrintWriter.println:(Ljava/lang/String;)V
       520: iload         6
       522: iload         5
       524: if_icmpeq     578
       527: iconst_0
       528: istore_2
       529: getstatic     #44                 // Field java/lang/System.err:Ljava/io/PrintStream;
       532: new           #29                 // class java/lang/StringBuilder
       535: dup
       536: invokespecial #30                 // Method java/lang/StringBuilder."<init>":()V
       539: ldc           #130                // String Line count validation failed for
       541: invokevirtual #31                 // Method java/lang/StringBuilder.append:(Ljava/lang/String;)Ljava/lang/StringBuilder;
       544: aload         4
       546: invokevirtual #31                 // Method java/lang/StringBuilder.append:(Ljava/lang/String;)Ljava/lang/StringBuilder;
       549: ldc           #131                // String , expecting
       551: invokevirtual #31                 // Method java/lang/StringBuilder.append:(Ljava/lang/String;)Ljava/lang/StringBuilder;
       554: iload         5
       556: invokevirtual #129                // Method java/lang/StringBuilder.append:(I)Ljava/lang/StringBuilder;
       559: ldc           #132                // String  found
       561: invokevirtual #31                 // Method java/lang/StringBuilder.append:(Ljava/lang/String;)Ljava/lang/StringBuilder;
       564: iload         6
       566: invokevirtual #129                // Method java/lang/StringBuilder.append:(I)Ljava/lang/StringBuilder;
       569: invokevirtual #33                 // Method java/lang/StringBuilder.toString:()Ljava/lang/String;
       572: invokevirtual #71                 // Method java/io/PrintStream.println:(Ljava/lang/String;)V
       575: goto          610
       578: getstatic     #62                 // Field verbose:Z
       581: ifeq          610
       584: getstatic     #36                 // Field java/lang/System.out:Ljava/io/PrintStream;
       587: new           #29                 // class java/lang/StringBuilder
       590: dup
       591: invokespecial #30                 // Method java/lang/StringBuilder."<init>":()V
       594: ldc           #133                // String Line count validation succeeded for
       596: invokevirtual #31                 // Method java/lang/StringBuilder.append:(Ljava/lang/String;)Ljava/lang/StringBuilder;
       599: aload         4
       601: invokevirtual #31                 // Method java/lang/StringBuilder.append:(Ljava/lang/String;)Ljava/lang/StringBuilder;
       604: invokevirtual #33                 // Method java/lang/StringBuilder.toString:()Ljava/lang/String;
       607: invokevirtual #71                 // Method java/io/PrintStream.println:(Ljava/lang/String;)V
       610: aload_0
       611: getfield      #10                 // Field config:Lorg/dacapo/parser/Config;
       614: aload_1
       615: aload         4
       617: invokevirtual #134                // Method org/dacapo/parser/Config.hasBytes:(Ljava/lang/String;Ljava/lang/String;)Z
       620: ifeq          842
       623: aload_0
       624: getfield      #10                 // Field config:Lorg/dacapo/parser/Config;
       627: aload_1
       628: aload         4
       630: invokevirtual #135                // Method org/dacapo/parser/Config.getBytes:(Ljava/lang/String;Ljava/lang/String;)J
       633: lstore        5
       635: new           #39                 // class java/io/File
       638: dup
       639: aload_0
       640: getfield      #24                 // Field scratch:Ljava/io/File;
       643: aload         4
       645: invokespecial #41                 // Method java/io/File."<init>":(Ljava/io/File;Ljava/lang/String;)V
       648: invokestatic  #136                // Method byteCount:(Ljava/io/File;)J
       651: lstore        7
       653: goto          704
       656: astore        9
       658: getstatic     #44                 // Field java/lang/System.err:Ljava/io/PrintStream;
       661: new           #29                 // class java/lang/StringBuilder
       664: dup
       665: invokespecial #30                 // Method java/lang/StringBuilder."<init>":()V
       668: ldc           #127                // String File not found,
       670: invokevirtual #31                 // Method java/lang/StringBuilder.append:(Ljava/lang/String;)Ljava/lang/StringBuilder;
       673: aload         4
       675: invokevirtual #31                 // Method java/lang/StringBuilder.append:(Ljava/lang/String;)Ljava/lang/StringBuilder;
       678: invokevirtual #33                 // Method java/lang/StringBuilder.toString:()Ljava/lang/String;
       681: invokevirtual #71                 // Method java/io/PrintStream.println:(Ljava/lang/String;)V
       684: ldc2_w        #137                // long -1l
       687: lstore        7
       689: goto          704
       692: astore        9
       694: aload         9
       696: invokevirtual #113                // Method java/io/IOException.printStackTrace:()V
       699: ldc2_w        #137                // long -1l
       702: lstore        7
       704: getstatic     #94                 // Field validationReport:Z
       707: ifeq          751
       710: getstatic     #95                 // Field valRepFile:Ljava/io/PrintWriter;
       713: new           #29                 // class java/lang/StringBuilder
       716: dup
       717: invokespecial #30                 // Method java/lang/StringBuilder."<init>":()V
       720: ldc           #114                // String   \"
       722: invokevirtual #31                 // Method java/lang/StringBuilder.append:(Ljava/lang/String;)Ljava/lang/StringBuilder;
       725: aload         4
       727: invokevirtual #31                 // Method java/lang/StringBuilder.append:(Ljava/lang/String;)Ljava/lang/StringBuilder;
       730: ldc           #139                // String \" bytes
       732: invokevirtual #31                 // Method java/lang/StringBuilder.append:(Ljava/lang/String;)Ljava/lang/StringBuilder;
       735: lload         7
       737: invokevirtual #140                // Method java/lang/StringBuilder.append:(J)Ljava/lang/StringBuilder;
       740: ldc           #116                // String ,
       742: invokevirtual #31                 // Method java/lang/StringBuilder.append:(Ljava/lang/String;)Ljava/lang/StringBuilder;
       745: invokevirtual #33                 // Method java/lang/StringBuilder.toString:()Ljava/lang/String;
       748: invokevirtual #97                 // Method java/io/PrintWriter.println:(Ljava/lang/String;)V
       751: lload         7
       753: lload         5
       755: lcmp
       756: ifeq          810
       759: iconst_0
       760: istore_2
       761: getstatic     #44                 // Field java/lang/System.err:Ljava/io/PrintStream;
       764: new           #29                 // class java/lang/StringBuilder
       767: dup
       768: invokespecial #30                 // Method java/lang/StringBuilder."<init>":()V
       771: ldc           #141                // String Byte count validation failed for
       773: invokevirtual #31                 // Method java/lang/StringBuilder.append:(Ljava/lang/String;)Ljava/lang/StringBuilder;
       776: aload         4
       778: invokevirtual #31                 // Method java/lang/StringBuilder.append:(Ljava/lang/String;)Ljava/lang/StringBuilder;
       781: ldc           #131                // String , expecting
       783: invokevirtual #31                 // Method java/lang/StringBuilder.append:(Ljava/lang/String;)Ljava/lang/StringBuilder;
       786: lload         5
       788: invokevirtual #140                // Method java/lang/StringBuilder.append:(J)Ljava/lang/StringBuilder;
       791: ldc           #132                // String  found
       793: invokevirtual #31                 // Method java/lang/StringBuilder.append:(Ljava/lang/String;)Ljava/lang/StringBuilder;
       796: lload         7
       798: invokevirtual #140                // Method java/lang/StringBuilder.append:(J)Ljava/lang/StringBuilder;
       801: invokevirtual #33                 // Method java/lang/StringBuilder.toString:()Ljava/lang/String;
       804: invokevirtual #71                 // Method java/io/PrintStream.println:(Ljava/lang/String;)V
       807: goto          842
       810: getstatic     #62                 // Field verbose:Z
       813: ifeq          842
       816: getstatic     #36                 // Field java/lang/System.out:Ljava/io/PrintStream;
       819: new           #29                 // class java/lang/StringBuilder
       822: dup
       823: invokespecial #30                 // Method java/lang/StringBuilder."<init>":()V
       826: ldc           #142                // String Byte count validation succeeded for
       828: invokevirtual #31                 // Method java/lang/StringBuilder.append:(Ljava/lang/String;)Ljava/lang/StringBuilder;
       831: aload         4
       833: invokevirtual #31                 // Method java/lang/StringBuilder.append:(Ljava/lang/String;)Ljava/lang/StringBuilder;
       836: invokevirtual #33                 // Method java/lang/StringBuilder.toString:()Ljava/lang/String;
       839: invokevirtual #71                 // Method java/io/PrintStream.println:(Ljava/lang/String;)V
       842: aload_0
       843: getfield      #10                 // Field config:Lorg/dacapo/parser/Config;
       846: aload_1
       847: aload         4
       849: invokevirtual #143                // Method org/dacapo/parser/Config.checkExists:(Ljava/lang/String;Ljava/lang/String;)Z
       852: ifeq          942
       855: new           #39                 // class java/io/File
       858: dup
       859: aload_0
       860: getfield      #24                 // Field scratch:Ljava/io/File;
       863: aload         4
       865: invokespecial #41                 // Method java/io/File."<init>":(Ljava/io/File;Ljava/lang/String;)V
       868: invokevirtual #54                 // Method java/io/File.exists:()Z
       871: ifne          910
       874: getstatic     #44                 // Field java/lang/System.err:Ljava/io/PrintStream;
       877: new           #29                 // class java/lang/StringBuilder
       880: dup
       881: invokespecial #30                 // Method java/lang/StringBuilder."<init>":()V
       884: ldc           #144                // String Expected file
       886: invokevirtual #31                 // Method java/lang/StringBuilder.append:(Ljava/lang/String;)Ljava/lang/StringBuilder;
       889: aload         4
       891: invokevirtual #31                 // Method java/lang/StringBuilder.append:(Ljava/lang/String;)Ljava/lang/StringBuilder;
       894: ldc           #145                // String  does not exist
       896: invokevirtual #31                 // Method java/lang/StringBuilder.append:(Ljava/lang/String;)Ljava/lang/StringBuilder;
       899: invokevirtual #33                 // Method java/lang/StringBuilder.toString:()Ljava/lang/String;
       902: invokevirtual #71                 // Method java/io/PrintStream.println:(Ljava/lang/String;)V
       905: iconst_0
       906: istore_2
       907: goto          942
       910: getstatic     #62                 // Field verbose:Z
       913: ifeq          942
       916: getstatic     #36                 // Field java/lang/System.out:Ljava/io/PrintStream;
       919: new           #29                 // class java/lang/StringBuilder
       922: dup
       923: invokespecial #30                 // Method java/lang/StringBuilder."<init>":()V
       926: ldc           #146                // String Existence validation succeeded for
       928: invokevirtual #31                 // Method java/lang/StringBuilder.append:(Ljava/lang/String;)Ljava/lang/StringBuilder;
       931: aload         4
       933: invokevirtual #31                 // Method java/lang/StringBuilder.append:(Ljava/lang/String;)Ljava/lang/StringBuilder;
       936: invokevirtual #33                 // Method java/lang/StringBuilder.toString:()Ljava/lang/String;
       939: invokevirtual #71                 // Method java/io/PrintStream.println:(Ljava/lang/String;)V
       942: goto          108
       945: getstatic     #94                 // Field validationReport:Z
       948: ifeq          957
       951: getstatic     #95                 // Field valRepFile:Ljava/io/PrintWriter;
       954: invokevirtual #147                // Method java/io/PrintWriter.flush:()V
       957: iload_2
       958: ireturn
      Exception table:
         from    to  target type
           153   191   194   Class java/io/FileNotFoundException
           153   191   203   Class java/io/IOException
           408   426   429   Class java/io/FileNotFoundException
           408   426   463   Class java/io/IOException
           635   653   656   Class java/io/FileNotFoundException
           635   653   692   Class java/io/IOException
      LineNumberTable:
        line 392: 0
        line 393: 6
        line 395: 38
        line 396: 44
        line 398: 46
        line 399: 52
        line 401: 92
        line 402: 94
        line 407: 128
        line 408: 141
        line 412: 153
        line 418: 191
        line 413: 194
        line 414: 196
        line 418: 200
        line 415: 203
        line 416: 205
        line 417: 209
        line 419: 214
        line 420: 220
        line 422: 261
        line 424: 290
        line 425: 300
        line 426: 302
        line 427: 351
        line 428: 357
        line 435: 383
        line 436: 396
        line 439: 408
        line 446: 426
        line 440: 429
        line 441: 431
        line 442: 457
        line 446: 460
        line 443: 463
        line 444: 465
        line 445: 470
        line 447: 473
        line 448: 479
        line 450: 520
        line 451: 527
        line 452: 529
        line 453: 578
        line 454: 584
        line 461: 610
        line 462: 623
        line 465: 635
        line 472: 653
        line 466: 656
        line 467: 658
        line 468: 684
        line 472: 689
        line 469: 692
        line 470: 694
        line 471: 699
        line 473: 704
        line 474: 710
        line 476: 751
        line 477: 759
        line 478: 761
        line 479: 810
        line 480: 816
        line 487: 842
        line 488: 855
        line 489: 874
        line 490: 905
        line 491: 910
        line 492: 916
        line 495: 942
        line 496: 945
        line 497: 951
        line 499: 957
      LocalVariableTable:
        Start  Length  Slot  Name   Signature
          191       3     6 digest   Ljava/lang/String;
          196       4     7     e   Ljava/io/FileNotFoundException;
          200       3     6 digest   Ljava/lang/String;
          205       9     7     e   Ljava/io/IOException;
          153     230     5 refDigest   Ljava/lang/String;
          209     174     6 digest   Ljava/lang/String;
          426       3     6 lines   I
          431      29     7     e   Ljava/io/FileNotFoundException;
          460       3     6 lines   I
          465       8     7     e   Ljava/io/IOException;
          408     202     5 refLines   I
          473     137     6 lines   I
          653       3     7 bytes   J
          658      31     9     e   Ljava/io/FileNotFoundException;
          689       3     7 bytes   J
          694      10     9     e   Ljava/io/IOException;
          635     207     5 refBytes   J
          704     138     7 bytes   J
          128     814     4  file   Ljava/lang/String;
            0     959     0  this   Lorg/dacapo/harness/Benchmark;
            0     959     1  size   Ljava/lang/String;
           94     865     2 valid   Z
      StackMapTable: number_of_entries = 27
        frame_type = 38 /* same */
        frame_type = 7 /* same */
        frame_type = 45 /* same */
        frame_type = 253 /* append */
          offset_delta = 15
          locals = [ int, class java/util/Iterator ]
        frame_type = 255 /* full_frame */
          offset_delta = 85
          locals = [ class org/dacapo/harness/Benchmark, class java/lang/String, int, class java/util/Iterator, class java/lang/String, class java/lang/String ]
          stack = [ class java/io/FileNotFoundException ]
        frame_type = 72 /* same_locals_1_stack_item */
          stack = [ class java/io/IOException ]
        frame_type = 252 /* append */
          offset_delta = 10
          locals = [ class java/lang/String ]
        frame_type = 46 /* same */
        frame_type = 28 /* same */
        frame_type = 60 /* same */
        frame_type = 249 /* chop */
          offset_delta = 31
        frame_type = 255 /* full_frame */
          offset_delta = 45
          locals = [ class org/dacapo/harness/Benchmark, class java/lang/String, int, class java/util/Iterator, class java/lang/String, int ]
          stack = [ class java/io/FileNotFoundException ]
        frame_type = 97 /* same_locals_1_stack_item */
          stack = [ class java/io/IOException ]
        frame_type = 252 /* append */
          offset_delta = 9
          locals = [ int ]
        frame_type = 46 /* same */
        frame_type = 57 /* same */
        frame_type = 249 /* chop */
          offset_delta = 31
        frame_type = 255 /* full_frame */
          offset_delta = 45
          locals = [ class org/dacapo/harness/Benchmark, class java/lang/String, int, class java/util/Iterator, class java/lang/String, long ]
          stack = [ class java/io/FileNotFoundException ]
        frame_type = 99 /* same_locals_1_stack_item */
          stack = [ class java/io/IOException ]
        frame_type = 252 /* append */
          offset_delta = 11
          locals = [ long ]
        frame_type = 46 /* same */
        frame_type = 58 /* same */
        frame_type = 249 /* chop */
          offset_delta = 31
        frame_type = 251 /* same_frame_extended */
          offset_delta = 67
        frame_type = 250 /* chop */
          offset_delta = 31
        frame_type = 250 /* chop */
          offset_delta = 2
        frame_type = 11 /* same */

  public void postIteration(java.lang.String) throws java.lang.Exception;
    descriptor: (Ljava/lang/String;)V
    flags: (0x0001) ACC_PUBLIC
    Code:
      stack=2, locals=2, args_size=2
         0: getstatic     #68                 // Field preserve:Z
         3: ifne          11
         6: aload_0
         7: aload_1
         8: invokevirtual #69                 // Method postIterationCleanup:(Ljava/lang/String;)V
        11: return
      LineNumberTable:
        line 509: 0
        line 510: 6
        line 512: 11
      LocalVariableTable:
        Start  Length  Slot  Name   Signature
            0      12     0  this   Lorg/dacapo/harness/Benchmark;
            0      12     1  size   Ljava/lang/String;
      StackMapTable: number_of_entries = 1
        frame_type = 11 /* same */
    Exceptions:
      throws java.lang.Exception

  protected void postIterationCleanup(java.lang.String);
    descriptor: (Ljava/lang/String;)V
    flags: (0x0004) ACC_PROTECTED
    Code:
      stack=4, locals=4, args_size=2
         0: aload_0
         1: getfield      #10                 // Field config:Lorg/dacapo/parser/Config;
         4: aload_1
         5: invokevirtual #98                 // Method org/dacapo/parser/Config.getOutputs:(Ljava/lang/String;)Ljava/util/Set;
         8: invokeinterface #99,  1           // InterfaceMethod java/util/Set.iterator:()Ljava/util/Iterator;
        13: astore_2
        14: aload_2
        15: invokeinterface #100,  1          // InterfaceMethod java/util/Iterator.hasNext:()Z
        20: ifeq          84
        23: aload_2
        24: invokeinterface #101,  1          // InterfaceMethod java/util/Iterator.next:()Ljava/lang/Object;
        29: checkcast     #102                // class java/lang/String
        32: astore_3
        33: aload_3
        34: ldc           #117                // String $stdout
        36: invokevirtual #118                // Method java/lang/String.equals:(Ljava/lang/Object;)Z
        39: ifne          81
        42: aload_3
        43: ldc           #119                // String $stderr
        45: invokevirtual #118                // Method java/lang/String.equals:(Ljava/lang/Object;)Z
        48: ifeq          54
        51: goto          81
        54: aload_0
        55: getfield      #10                 // Field config:Lorg/dacapo/parser/Config;
        58: aload_1
        59: aload_3
        60: invokevirtual #148                // Method org/dacapo/parser/Config.isKept:(Ljava/lang/String;Ljava/lang/String;)Z
        63: ifne          81
        66: new           #39                 // class java/io/File
        69: dup
        70: aload_0
        71: getfield      #24                 // Field scratch:Ljava/io/File;
        74: aload_3
        75: invokespecial #41                 // Method java/io/File."<init>":(Ljava/io/File;Ljava/lang/String;)V
        78: invokestatic  #149                // Method deleteFile:(Ljava/io/File;)V
        81: goto          14
        84: return
      LineNumberTable:
        line 520: 0
        line 521: 33
        line 523: 54
        line 524: 66
        line 526: 81
        line 527: 84
      LocalVariableTable:
        Start  Length  Slot  Name   Signature
           33      48     3  file   Ljava/lang/String;
            0      85     0  this   Lorg/dacapo/harness/Benchmark;
            0      85     1  size   Ljava/lang/String;
      StackMapTable: number_of_entries = 4
        frame_type = 252 /* append */
          offset_delta = 14
          locals = [ class java/util/Iterator ]
        frame_type = 252 /* append */
          offset_delta = 39
          locals = [ class java/lang/String ]
        frame_type = 250 /* chop */
          offset_delta = 26
        frame_type = 250 /* chop */
          offset_delta = 2

  public void cleanup();
    descriptor: ()V
    flags: (0x0001) ACC_PUBLIC
    Code:
      stack=4, locals=1, args_size=1
         0: getstatic     #68                 // Field preserve:Z
         3: ifne          27
         6: new           #39                 // class java/io/File
         9: dup
        10: aload_0
        11: getfield      #24                 // Field scratch:Ljava/io/File;
        14: aload_0
        15: getfield      #10                 // Field config:Lorg/dacapo/parser/Config;
        18: getfield      #11                 // Field org/dacapo/parser/Config.name:Ljava/lang/String;
        21: invokespecial #41                 // Method java/io/File."<init>":(Ljava/io/File;Ljava/lang/String;)V
        24: invokestatic  #150                // Method deleteTree:(Ljava/io/File;)V
        27: return
      LineNumberTable:
        line 535: 0
        line 536: 6
        line 538: 27
      LocalVariableTable:
        Start  Length  Slot  Name   Signature
            0      28     0  this   Lorg/dacapo/harness/Benchmark;
      StackMapTable: number_of_entries = 1
        frame_type = 27 /* same */

  public static java.net.URL getURL(java.lang.String);
    descriptor: (Ljava/lang/String;)Ljava/net/URL;
    flags: (0x0009) ACC_PUBLIC, ACC_STATIC
    Code:
      stack=3, locals=3, args_size=1
         0: ldc           #72                 // class org/dacapo/harness/Benchmark
         2: invokevirtual #151                // Method java/lang/Class.getClassLoader:()Ljava/lang/ClassLoader;
         5: astore_1
         6: aload_1
         7: aload_0
         8: invokevirtual #152                // Method java/lang/ClassLoader.getResource:(Ljava/lang/String;)Ljava/net/URL;
        11: astore_2
        12: getstatic     #62                 // Field verbose:Z
        15: ifeq          43
        18: getstatic     #36                 // Field java/lang/System.out:Ljava/io/PrintStream;
        21: new           #29                 // class java/lang/StringBuilder
        24: dup
        25: invokespecial #30                 // Method java/lang/StringBuilder."<init>":()V
        28: ldc           #153                // String Util.getURL: returns
        30: invokevirtual #31                 // Method java/lang/StringBuilder.append:(Ljava/lang/String;)Ljava/lang/StringBuilder;
        33: aload_2
        34: invokevirtual #51                 // Method java/lang/StringBuilder.append:(Ljava/lang/Object;)Ljava/lang/StringBuilder;
        37: invokevirtual #33                 // Method java/lang/StringBuilder.toString:()Ljava/lang/String;
        40: invokevirtual #71                 // Method java/io/PrintStream.println:(Ljava/lang/String;)V
        43: aload_2
        44: areturn
      LineNumberTable:
        line 551: 0
        line 552: 6
        line 553: 12
        line 554: 18
        line 555: 43
      LocalVariableTable:
        Start  Length  Slot  Name   Signature
            0      45     0    fn   Ljava/lang/String;
            6      39     1    cl   Ljava/lang/ClassLoader;
           12      33     2 resource   Ljava/net/URL;
      StackMapTable: number_of_entries = 1
        frame_type = 253 /* append */
          offset_delta = 43
          locals = [ class java/lang/ClassLoader, class java/net/URL ]

  public java.lang.String fileInScratch(java.lang.String);
    descriptor: (Ljava/lang/String;)Ljava/lang/String;
    flags: (0x0001) ACC_PUBLIC
    Code:
      stack=4, locals=2, args_size=2
         0: new           #39                 // class java/io/File
         3: dup
         4: aload_0
         5: getfield      #24                 // Field scratch:Ljava/io/File;
         8: aload_1
         9: invokespecial #41                 // Method java/io/File."<init>":(Ljava/io/File;Ljava/lang/String;)V
        12: invokevirtual #154                // Method java/io/File.getPath:()Ljava/lang/String;
        15: areturn
      LineNumberTable:
        line 565: 0
      LocalVariableTable:
        Start  Length  Slot  Name   Signature
            0      16     0  this   Lorg/dacapo/harness/Benchmark;
            0      16     1  name   Ljava/lang/String;

  public static void unpackZipFileResource(java.lang.String, java.io.File) throws java.io.IOException, java.io.FileNotFoundException, org.dacapo.harness.DacapoException;
    descriptor: (Ljava/lang/String;Ljava/io/File;)V
    flags: (0x0009) ACC_PUBLIC, ACC_STATIC
    Code:
      stack=4, locals=4, args_size=2
         0: aload_0
         1: invokestatic  #155                // Method getURL:(Ljava/lang/String;)Ljava/net/URL;
         4: astore_2
         5: aload_2
         6: ifnonnull     41
         9: new           #156                // class org/dacapo/harness/DacapoException
        12: dup
        13: new           #29                 // class java/lang/StringBuilder
        16: dup
        17: invokespecial #30                 // Method java/lang/StringBuilder."<init>":()V
        20: ldc           #157                // String No such zip file: \"
        22: invokevirtual #31                 // Method java/lang/StringBuilder.append:(Ljava/lang/String;)Ljava/lang/StringBuilder;
        25: aload_0
        26: invokevirtual #31                 // Method java/lang/StringBuilder.append:(Ljava/lang/String;)Ljava/lang/StringBuilder;
        29: ldc           #158                // String \"
        31: invokevirtual #31                 // Method java/lang/StringBuilder.append:(Ljava/lang/String;)Ljava/lang/StringBuilder;
        34: invokevirtual #33                 // Method java/lang/StringBuilder.toString:()Ljava/lang/String;
        37: invokespecial #159                // Method org/dacapo/harness/DacapoException."<init>":(Ljava/lang/String;)V
        40: athrow
        41: new           #160                // class java/io/BufferedInputStream
        44: dup
        45: aload_2
        46: invokevirtual #161                // Method java/net/URL.openStream:()Ljava/io/InputStream;
        49: invokespecial #162                // Method java/io/BufferedInputStream."<init>":(Ljava/io/InputStream;)V
        52: astore_3
        53: aload_3
        54: aload_1
        55: invokestatic  #163                // Method unpackZipStream:(Ljava/io/BufferedInputStream;Ljava/io/File;)V
        58: return
      LineNumberTable:
        line 577: 0
        line 578: 5
        line 579: 9
        line 581: 41
        line 582: 53
        line 583: 58
      LocalVariableTable:
        Start  Length  Slot  Name   Signature
            0      59     0  name   Ljava/lang/String;
            0      59     1 destination   Ljava/io/File;
            5      54     2 resource   Ljava/net/URL;
           53       6     3 inputStream   Ljava/io/BufferedInputStream;
      StackMapTable: number_of_entries = 1
        frame_type = 252 /* append */
          offset_delta = 41
          locals = [ class java/net/URL ]
    Exceptions:
      throws java.io.IOException, java.io.FileNotFoundException, org.dacapo.harness.DacapoException

  public static void extractFileResource(java.lang.String, java.io.File) throws java.io.IOException, java.io.FileNotFoundException, org.dacapo.harness.DacapoException;
    descriptor: (Ljava/lang/String;Ljava/io/File;)V
    flags: (0x0009) ACC_PUBLIC, ACC_STATIC
    Code:
      stack=5, locals=4, args_size=2
         0: getstatic     #62                 // Field verbose:Z
         3: ifeq          43
         6: getstatic     #36                 // Field java/lang/System.out:Ljava/io/PrintStream;
         9: new           #29                 // class java/lang/StringBuilder
        12: dup
        13: invokespecial #30                 // Method java/lang/StringBuilder."<init>":()V
        16: ldc           #164                // String Extracting file
        18: invokevirtual #31                 // Method java/lang/StringBuilder.append:(Ljava/lang/String;)Ljava/lang/StringBuilder;
        21: aload_0
        22: invokevirtual #31                 // Method java/lang/StringBuilder.append:(Ljava/lang/String;)Ljava/lang/StringBuilder;
        25: ldc           #165                // String  into
        27: invokevirtual #31                 // Method java/lang/StringBuilder.append:(Ljava/lang/String;)Ljava/lang/StringBuilder;
        30: aload_1
        31: invokevirtual #166                // Method java/io/File.getCanonicalPath:()Ljava/lang/String;
        34: invokevirtual #31                 // Method java/lang/StringBuilder.append:(Ljava/lang/String;)Ljava/lang/StringBuilder;
        37: invokevirtual #33                 // Method java/lang/StringBuilder.toString:()Ljava/lang/String;
        40: invokevirtual #71                 // Method java/io/PrintStream.println:(Ljava/lang/String;)V
        43: aload_0
        44: invokestatic  #155                // Method getURL:(Ljava/lang/String;)Ljava/net/URL;
        47: astore_2
        48: aload_2
        49: ifnonnull     84
        52: new           #156                // class org/dacapo/harness/DacapoException
        55: dup
        56: new           #29                 // class java/lang/StringBuilder
        59: dup
        60: invokespecial #30                 // Method java/lang/StringBuilder."<init>":()V
        63: ldc           #167                // String No such file: \"
        65: invokevirtual #31                 // Method java/lang/StringBuilder.append:(Ljava/lang/String;)Ljava/lang/StringBuilder;
        68: aload_0
        69: invokevirtual #31                 // Method java/lang/StringBuilder.append:(Ljava/lang/String;)Ljava/lang/StringBuilder;
        72: ldc           #158                // String \"
        74: invokevirtual #31                 // Method java/lang/StringBuilder.append:(Ljava/lang/String;)Ljava/lang/StringBuilder;
        77: invokevirtual #33                 // Method java/lang/StringBuilder.toString:()Ljava/lang/String;
        80: invokespecial #159                // Method org/dacapo/harness/DacapoException."<init>":(Ljava/lang/String;)V
        83: athrow
        84: new           #160                // class java/io/BufferedInputStream
        87: dup
        88: aload_2
        89: invokevirtual #161                // Method java/net/URL.openStream:()Ljava/io/InputStream;
        92: invokespecial #162                // Method java/io/BufferedInputStream."<init>":(Ljava/io/InputStream;)V
        95: astore_3
        96: aload_3
        97: new           #39                 // class java/io/File
       100: dup
       101: aload_1
       102: aload_0
       103: invokespecial #41                 // Method java/io/File."<init>":(Ljava/io/File;Ljava/lang/String;)V
       106: invokestatic  #168                // Method fileFromInputStream:(Ljava/io/InputStream;Ljava/io/File;)V
       109: return
      LineNumberTable:
        line 586: 0
        line 587: 6
        line 588: 43
        line 589: 48
        line 590: 52
        line 591: 84
        line 592: 96
        line 593: 109
      LocalVariableTable:
        Start  Length  Slot  Name   Signature
            0     110     0  name   Ljava/lang/String;
            0     110     1 destination   Ljava/io/File;
           48      62     2 resource   Ljava/net/URL;
           96      14     3 inputStream   Ljava/io/BufferedInputStream;
      StackMapTable: number_of_entries = 2
        frame_type = 43 /* same */
        frame_type = 252 /* append */
          offset_delta = 40
          locals = [ class java/net/URL ]
    Exceptions:
      throws java.io.IOException, java.io.FileNotFoundException, org.dacapo.harness.DacapoException

  public static void deleteTree(java.io.File);
    descriptor: (Ljava/io/File;)V
    flags: (0x0009) ACC_PUBLIC, ACC_STATIC
    Code:
      stack=3, locals=3, args_size=1
         0: getstatic     #62                 // Field verbose:Z
         3: ifeq          34
         6: getstatic     #36                 // Field java/lang/System.out:Ljava/io/PrintStream;
         9: new           #29                 // class java/lang/StringBuilder
        12: dup
        13: invokespecial #30                 // Method java/lang/StringBuilder."<init>":()V
        16: ldc           #184                // String Deleting
        18: invokevirtual #31                 // Method java/lang/StringBuilder.append:(Ljava/lang/String;)Ljava/lang/StringBuilder;
        21: aload_0
        22: invokevirtual #185                // Method java/io/File.getName:()Ljava/lang/String;
        25: invokevirtual #31                 // Method java/lang/StringBuilder.append:(Ljava/lang/String;)Ljava/lang/StringBuilder;
        28: invokevirtual #33                 // Method java/lang/StringBuilder.toString:()Ljava/lang/String;
        31: invokevirtual #71                 // Method java/io/PrintStream.println:(Ljava/lang/String;)V
        34: aload_0
        35: invokevirtual #186                // Method java/io/File.isDirectory:()Z
        38: ifne          49
        41: aload_0
        42: invokevirtual #187                // Method java/io/File.delete:()Z
        45: pop
        46: goto          79
        49: aload_0
        50: invokevirtual #188                // Method java/io/File.listFiles:()[Ljava/io/File;
        53: astore_1
        54: iconst_0
        55: istore_2
        56: iload_2
        57: aload_1
        58: arraylength
        59: if_icmpge     74
        62: aload_1
        63: iload_2
        64: aaload
        65: invokestatic  #150                // Method deleteTree:(Ljava/io/File;)V
        68: iinc          2, 1
        71: goto          56
        74: aload_0
        75: invokevirtual #187                // Method java/io/File.delete:()Z
        78: pop
        79: return
      LineNumberTable:
        line 630: 0
        line 631: 6
        line 632: 34
        line 633: 41
        line 635: 49
        line 636: 54
        line 637: 62
        line 636: 68
        line 638: 74
        line 640: 79
      LocalVariableTable:
        Start  Length  Slot  Name   Signature
           56      18     2     i   I
           54      25     1 files   [Ljava/io/File;
            0      80     0  tree   Ljava/io/File;
      StackMapTable: number_of_entries = 5
        frame_type = 34 /* same */
        frame_type = 14 /* same */
        frame_type = 253 /* append */
          offset_delta = 6
          locals = [ class "[Ljava/io/File;", int ]
        frame_type = 250 /* chop */
          offset_delta = 17
        frame_type = 250 /* chop */
          offset_delta = 4

  public static void deleteFile(java.io.File);
    descriptor: (Ljava/io/File;)V
    flags: (0x0009) ACC_PUBLIC, ACC_STATIC
    Code:
      stack=3, locals=1, args_size=1
         0: getstatic     #62                 // Field verbose:Z
         3: ifeq          34
         6: getstatic     #36                 // Field java/lang/System.out:Ljava/io/PrintStream;
         9: new           #29                 // class java/lang/StringBuilder
        12: dup
        13: invokespecial #30                 // Method java/lang/StringBuilder."<init>":()V
        16: ldc           #184                // String Deleting
        18: invokevirtual #31                 // Method java/lang/StringBuilder.append:(Ljava/lang/String;)Ljava/lang/StringBuilder;
        21: aload_0
        22: invokevirtual #185                // Method java/io/File.getName:()Ljava/lang/String;
        25: invokevirtual #31                 // Method java/lang/StringBuilder.append:(Ljava/lang/String;)Ljava/lang/StringBuilder;
        28: invokevirtual #33                 // Method java/lang/StringBuilder.toString:()Ljava/lang/String;
        31: invokevirtual #71                 // Method java/io/PrintStream.println:(Ljava/lang/String;)V
        34: aload_0
        35: invokevirtual #54                 // Method java/io/File.exists:()Z
        38: ifeq          53
        41: aload_0
        42: invokevirtual #186                // Method java/io/File.isDirectory:()Z
        45: ifne          53
        48: aload_0
        49: invokevirtual #187                // Method java/io/File.delete:()Z
        52: pop
        53: return
      LineNumberTable:
        line 643: 0
        line 644: 6
        line 645: 34
        line 646: 48
        line 647: 53
      LocalVariableTable:
        Start  Length  Slot  Name   Signature
            0      54     0  file   Ljava/io/File;
      StackMapTable: number_of_entries = 2
        frame_type = 34 /* same */
        frame_type = 18 /* same */

  public static int lineCount(java.io.File) throws java.io.IOException;
    descriptor: (Ljava/io/File;)I
    flags: (0x0009) ACC_PUBLIC, ACC_STATIC
    Code:
      stack=5, locals=3, args_size=1
         0: iconst_0
         1: istore_1
         2: new           #189                // class java/io/BufferedReader
         5: dup
         6: new           #190                // class java/io/FileReader
         9: dup
        10: aload_0
        11: invokespecial #191                // Method java/io/FileReader."<init>":(Ljava/io/File;)V
        14: invokespecial #192                // Method java/io/BufferedReader."<init>":(Ljava/io/Reader;)V
        17: astore_2
        18: aload_2
        19: invokevirtual #193                // Method java/io/BufferedReader.readLine:()Ljava/lang/String;
        22: ifnull        31
        25: iinc          1, 1
        28: goto          18
        31: aload_2
        32: invokevirtual #194                // Method java/io/BufferedReader.close:()V
        35: iload_1
        36: ireturn
      LineNumberTable:
        line 650: 0
        line 651: 2
        line 652: 18
        line 653: 25
        line 654: 31
        line 655: 35
      LocalVariableTable:
        Start  Length  Slot  Name   Signature
            0      37     0  file   Ljava/io/File;
            2      35     1 lines   I
           18      19     2    in   Ljava/io/BufferedReader;
      StackMapTable: number_of_entries = 2
        frame_type = 253 /* append */
          offset_delta = 18
          locals = [ int, class java/io/BufferedReader ]
        frame_type = 12 /* same */
    Exceptions:
      throws java.io.IOException

  public static long byteCount(java.io.File) throws java.io.IOException;
    descriptor: (Ljava/io/File;)J
    flags: (0x0009) ACC_PUBLIC, ACC_STATIC
    Code:
      stack=2, locals=1, args_size=1
         0: aload_0
         1: invokevirtual #195                // Method java/io/File.length:()J
         4: lreturn
      LineNumberTable:
        line 659: 0
      LocalVariableTable:
        Start  Length  Slot  Name   Signature
            0       5     0  file   Ljava/io/File;
    Exceptions:
      throws java.io.IOException

  public static void setCommandLineOptions(org.dacapo.harness.CommandLineArgs);
    descriptor: (Lorg/dacapo/harness/CommandLineArgs;)V
    flags: (0x0009) ACC_PUBLIC, ACC_STATIC
    Code:
      stack=1, locals=1, args_size=1
         0: aload_0
         1: invokevirtual #196                // Method org/dacapo/harness/CommandLineArgs.getSilent:()Z
         4: putstatic     #23                 // Field silent:Z
         7: aload_0
         8: invokevirtual #197                // Method org/dacapo/harness/CommandLineArgs.getPreserve:()Z
        11: putstatic     #68                 // Field preserve:Z
        14: aload_0
        15: invokevirtual #198                // Method org/dacapo/harness/CommandLineArgs.getValidate:()Z
        18: putstatic     #91                 // Field validate:Z
        21: aload_0
        22: invokevirtual #199                // Method org/dacapo/harness/CommandLineArgs.getValidateOutput:()Z
        25: putstatic     #79                 // Field validateOutput:Z
        28: aload_0
        29: invokevirtual #200                // Method org/dacapo/harness/CommandLineArgs.getPreIterationGC:()Z
        32: putstatic     #8                  // Field preIterationGC:Z
        35: aload_0
        36: invokevirtual #201                // Method org/dacapo/harness/CommandLineArgs.getTimeoutDialation:()Ljava/lang/String;
        39: putstatic     #74                 // Field timeoutDialation:Ljava/lang/String;
        42: aload_0
        43: invokevirtual #202                // Method org/dacapo/harness/CommandLineArgs.getValidationReport:()Ljava/lang/String;
        46: ifnull        56
        49: aload_0
        50: invokevirtual #202                // Method org/dacapo/harness/CommandLineArgs.getValidationReport:()Ljava/lang/String;
        53: invokestatic  #203                // Method enableValidationReport:(Ljava/lang/String;)V
        56: return
      LineNumberTable:
        line 663: 0
        line 664: 7
        line 665: 14
        line 666: 21
        line 667: 28
        line 668: 35
        line 669: 42
        line 670: 49
        line 671: 56
      LocalVariableTable:
        Start  Length  Slot  Name   Signature
            0      57     0  line   Lorg/dacapo/harness/CommandLineArgs;
      StackMapTable: number_of_entries = 1
        frame_type = 56 /* same */

  public static boolean getVerbose();
    descriptor: ()Z
    flags: (0x0009) ACC_PUBLIC, ACC_STATIC
    Code:
      stack=1, locals=0, args_size=0
         0: getstatic     #62                 // Field verbose:Z
         3: ireturn
      LineNumberTable:
        line 686: 0

  public static boolean getValidateOutput();
    descriptor: ()Z
    flags: (0x0009) ACC_PUBLIC, ACC_STATIC
    Code:
      stack=1, locals=0, args_size=0
         0: getstatic     #79                 // Field validateOutput:Z
         3: ireturn
      LineNumberTable:
        line 690: 0

  public static boolean getValidate();
    descriptor: ()Z
    flags: (0x0009) ACC_PUBLIC, ACC_STATIC
    Code:
      stack=1, locals=0, args_size=0
         0: getstatic     #91                 // Field validate:Z
         3: ireturn
      LineNumberTable:
        line 694: 0

  public static boolean getPreserve();
    descriptor: ()Z
    flags: (0x0009) ACC_PUBLIC, ACC_STATIC
    Code:
      stack=1, locals=0, args_size=0
         0: getstatic     #68                 // Field preserve:Z
         3: ireturn
      LineNumberTable:
        line 698: 0

  protected int getIteration();
    descriptor: ()I
    flags: (0x0004) ACC_PROTECTED
    Code:
      stack=1, locals=1, args_size=1
         0: aload_0
         1: getfield      #1                  // Field iteration:I
         4: ireturn
      LineNumberTable:
        line 702: 0
      LocalVariableTable:
        Start  Length  Slot  Name   Signature
            0       5     0  this   Lorg/dacapo/harness/Benchmark;

  public static boolean getSilent();
    descriptor: ()Z
    flags: (0x0009) ACC_PUBLIC, ACC_STATIC
    Code:
      stack=1, locals=0, args_size=0
         0: getstatic     #23                 // Field silent:Z
         3: ireturn
      LineNumberTable:
        line 706: 0

  static {};
    descriptor: ()V
    flags: (0x0008) ACC_STATIC
    Code:
      stack=1, locals=0, args_size=0
         0: iconst_0
         1: putstatic     #62                 // Field verbose:Z
         4: iconst_1
         5: putstatic     #23                 // Field silent:Z
         8: iconst_1
         9: putstatic     #79                 // Field validateOutput:Z
        12: iconst_0
        13: putstatic     #8                  // Field preIterationGC:Z
        16: iconst_1
        17: putstatic     #91                 // Field validate:Z
        20: iconst_0
        21: putstatic     #68                 // Field preserve:Z
        24: aconst_null
        25: putstatic     #95                 // Field valRepFile:Ljava/io/PrintWriter;
        28: iconst_0
        29: putstatic     #94                 // Field validationReport:Z
        32: ldc           #211                // String 1
        34: putstatic     #74                 // Field timeoutDialation:Ljava/lang/String;
        37: getstatic     #36                 // Field java/lang/System.out:Ljava/io/PrintStream;
        40: putstatic     #3                  // Field savedOut:Ljava/io/PrintStream;
        43: getstatic     #44                 // Field java/lang/System.err:Ljava/io/PrintStream;
        46: putstatic     #5                  // Field savedErr:Ljava/io/PrintStream;
        49: aconst_null
        50: putstatic     #45                 // Field err:Lorg/dacapo/harness/TeePrintStream;
        53: aconst_null
        54: putstatic     #37                 // Field out:Lorg/dacapo/harness/TeePrintStream;
        57: return
      LineNumberTable:
        line 50: 0
        line 55: 4
        line 60: 8
        line 65: 12
        line 70: 16
        line 75: 20
        line 80: 24
        line 85: 28
        line 92: 32
        line 97: 37
        line 102: 43
        line 136: 49
        line 141: 53
}
SourceFile: "Benchmark.java"
